src/aggregate.sv

`default_nettype none
`timescale 1ns / 1ps
module aggregate(
	input wire clk,
	input wire rst,
	input wire axiiv,
	input wire [1:0] axiid,
	output logic axiov,
	output logic [31:0] axiod
);

logic [2:0] now_state;
logic [4:0] id;
logic[31:0] axiod_buffer_first;
logic[31:0] axiod_buffer_second;
always_ff @(posedge clk)begin
	if(rst)begin
		now_state <= 3'b001;
		id <= 0;
		axiod_buffer_first <= 0;
		axiod_buffer_second <= 0;
		axiov <= 0;
		axiod <= 0;
	end

	if(now_state == 3'b001)begin
		if(axiiv)begin
			now_state <= 3'b010;
			axiod_buffer_first[31:30] <= axiid;
			id <= 28;
		end
		axiov <= 0;
	end
	else if(now_state == 3'b010)begin
		if(axiiv)begin
			axiod_buffer_first[id+:2] <= axiid;
			if(id == 0)begin
				id <= 30;
				now_state <= 3'b100;
			end else begin
				id <= id -2;
			end
		end else begin
			id <= 0;
			axiod_buffer_first <= 0;
			axiov <= 0;
			now_state <= 3'b001;
		end
	end else if(now_state == 3'b100)begin
		if(axiiv)begin
			axiod_buffer_second[id+:2] <= axiid;
			if(id == 0)begin
				axiov <= 1;
				id <= 29;
				axiod <= axiod_buffer_first;
				axiod_buffer_first <= {axiod_buffer_second[31:2],axiid};
			end else begin
				id <= id - 2;
				axiov <= 0;
			end
		end else begin
			id <= 0;
			axiod_buffer_second <= 0;
			axiod_buffer_first <= 0;
			axiov <= 0;
			now_state <= 3'b001;
		end	
	end
end

endmodule
`default_nettype wire

sim/aggregate_tb.sv
`default_nettype none
`timescale 1ns / 1ps
module aggregate_tb;
	logic clk;
	logic rst;
	logic [1:0] axiid;
	logic axiiv;
	logic [31:0] axiod;
	logic axiov;
	// logic[95:0] message;
	aggregate uut(
		.clk(clk),
		.rst(rst),
		.axiid(axiid),
		.axiiv(axiiv),
		.axiod(axiod),
		.axiov(axiov)
	);

	always begin
        #10;
        clk = !clk;
    end
	initial begin
		$display("Starting Sim");
		$dumpfile("aggregate.vcd");
		$dumpvars(0,aggregate_tb);
		clk = 0;
		rst = 0;
		axiid = 0;
		axiiv = 0; 

		rst = 1;
		#20;
		rst = 0;

		//test case 1
		axiiv = 1;
		axiid = 2'b10;
		for(int x = 30; x>=0; x=x-2)begin
			axiid = 2'b10;
			#20;
		end
		axiid = 2'b11;
		for(int x = 62; x>=0; x=x-2)begin
			if(x >= 34)
				axiid = 2'b10;
			else
				axiid = 2'b11;
			#20;
		end
		#100;
		axiid = 2;
		#20;
		axiiv = 0;
		#80
		$display("Finishing Sim");
		$finish;
	end
endmodule
`default_nettype wire

aggregate.vcd
$date
	Tue Nov  1 11:51:59 2022
$end
$version
	Icarus Verilog
$end
$timescale
	1ps
$end
$scope module aggregate_tb $end
$var wire 1 ! axiov $end
$var wire 32 " axiod [31:0] $end
$var reg 2 # axiid [1:0] $end
$var reg 1 $ axiiv $end
$var reg 1 % clk $end
$var reg 1 & rst $end
$scope module uut $end
$var wire 2 ' axiid [1:0] $end
$var wire 1 $ axiiv $end
$var wire 1 % clk $end
$var wire 1 & rst $end
$var reg 32 ( axiod [31:0] $end
$var reg 32 ) axiod_buffer_first [31:0] $end
$var reg 32 * axiod_buffer_second [31:0] $end
$var reg 1 ! axiov $end
$var reg 5 + id [4:0] $end
$var reg 3 , now_state [2:0] $end
$upscope $end
$scope begin $ivl_for_loop0 $end
$var integer 32 - x [31:0] $end
$upscope $end
$scope begin $ivl_for_loop1 $end
$var integer 32 . x [31:0] $end
$upscope $end
$upscope $end
$enddefinitions $end
#0
$dumpvars
b0 .
b0 -
bx ,
bx +
bx *
bx )
bx (
b0 '
1&
0%
0$
b0 #
bx "
x!
$end
#10000
b0 "
b0 (
0!
b0 *
b0 )
b0 +
b1 ,
1%
#20000
0%
b11110 -
b10 #
b10 '
1$
0&
#30000
b11100 +
b10000000000000000000000000000000 )
b10 ,
1%
#40000
0%
b11100 -
#50000
b11010 +
b10100000000000000000000000000000 )
1%
#60000
0%
b11010 -
#70000
b11000 +
b10101000000000000000000000000000 )
1%
#80000
0%
b11000 -
#90000
b10110 +
b10101010000000000000000000000000 )
1%
#100000
0%
b10110 -
#110000
b10100 +
b10101010100000000000000000000000 )
1%
#120000
0%
b10100 -
#130000
b10010 +
b10101010101000000000000000000000 )
1%
#140000
0%
b10010 -
#150000
b10000 +
b10101010101010000000000000000000 )
1%
#160000
0%
b10000 -
#170000
b1110 +
b10101010101010100000000000000000 )
1%
#180000
0%
b1110 -
#190000
b1100 +
b10101010101010101000000000000000 )
1%
#200000
0%
b1100 -
#210000
b1010 +
b10101010101010101010000000000000 )
1%
#220000
0%
b1010 -
#230000
b1000 +
b10101010101010101010100000000000 )
1%
#240000
0%
b1000 -
#250000
b110 +
b10101010101010101010101000000000 )
1%
#260000
0%
b110 -
#270000
b100 +
b10101010101010101010101010000000 )
1%
#280000
0%
b100 -
#290000
b10 +
b10101010101010101010101010100000 )
1%
#300000
0%
b10 -
#310000
b0 +
b10101010101010101010101010101000 )
1%
#320000
0%
b0 -
#330000
b100 ,
b11110 +
b10101010101010101010101010101010 )
1%
#340000
0%
b111110 .
b10 #
b10 '
b11111111111111111111111111111110 -
#350000
b11100 +
b10000000000000000000000000000000 *
1%
#360000
0%
b111100 .
#370000
b11010 +
b10100000000000000000000000000000 *
1%
#380000
0%
b111010 .
#390000
b11000 +
b10101000000000000000000000000000 *
1%
#400000
0%
b111000 .
#410000
b10110 +
b10101010000000000000000000000000 *
1%
#420000
0%
b110110 .
#430000
b10100 +
b10101010100000000000000000000000 *
1%
#440000
0%
b110100 .
#450000
b10010 +
b10101010101000000000000000000000 *
1%
#460000
0%
b110010 .
#470000
b10000 +
b10101010101010000000000000000000 *
1%
#480000
0%
b110000 .
#490000
b1110 +
b10101010101010100000000000000000 *
1%
#500000
0%
b101110 .
#510000
b1100 +
b10101010101010101000000000000000 *
1%
#520000
0%
b101100 .
#530000
b1010 +
b10101010101010101010000000000000 *
1%
#540000
0%
b101010 .
#550000
b1000 +
b10101010101010101010100000000000 *
1%
#560000
0%
b101000 .
#570000
b110 +
b10101010101010101010101000000000 *
1%
#580000
0%
b100110 .
#590000
b100 +
b10101010101010101010101010000000 *
1%
#600000
0%
b100100 .
#610000
b10 +
b10101010101010101010101010100000 *
1%
#620000
0%
b100010 .
#630000
b0 +
b10101010101010101010101010101000 *
1%
#640000
0%
b11 #
b11 '
b100000 .
#650000
b10101010101010101010101010101011 )
b10101010101010101010101010101010 "
b10101010101010101010101010101010 (
b11101 +
1!
b10101010101010101010101010101011 *
1%
#660000
0%
b11110 .
#670000
0!
b11011 +
b11101010101010101010101010101011 *
1%
#680000
0%
b11100 .
#690000
b11001 +
b11111010101010101010101010101011 *
1%
#700000
0%
b11010 .
#710000
b10111 +
b11111110101010101010101010101011 *
1%
#720000
0%
b11000 .
#730000
b10101 +
b11111111101010101010101010101011 *
1%
#740000
0%
b10110 .
#750000
b10011 +
b11111111111010101010101010101011 *
1%
#760000
0%
b10100 .
#770000
b10001 +
b11111111111110101010101010101011 *
1%
#780000
0%
b10010 .
#790000
b1111 +
b11111111111111101010101010101011 *
1%
#800000
0%
b10000 .
#810000
b1101 +
b11111111111111111010101010101011 *
1%
#820000
0%
b1110 .
#830000
b1011 +
b11111111111111111110101010101011 *
1%
#840000
0%
b1100 .
#850000
b1001 +
b11111111111111111111101010101011 *
1%
#860000
0%
b1010 .
#870000
b111 +
b11111111111111111111111010101011 *
1%
#880000
0%
b1000 .
#890000
b101 +
b11111111111111111111111110101011 *
1%
#900000
0%
b110 .
#910000
b11 +
b11111111111111111111111111101011 *
1%
#920000
0%
b100 .
#930000
b1 +
b11111111111111111111111111111011 *
1%
#940000
0%
b10 .
#950000
b11111 +
b11111111111111111111111111111111 *
1%
#960000
0%
b0 .
#970000
b11101 +
1%
#980000
0%
b11111111111111111111111111111110 .
#990000
b11011 +
1%
#1000000
0%
#1010000
b11001 +
1%
#1020000
0%
#1030000
b10111 +
1%
#1040000
0%
#1050000
b10101 +
1%
#1060000
0%
#1070000
b10011 +
1%
#1080000
0%
b10 #
b10 '
#1090000
b10001 +
b11111111111101111111111111111111 *
1%
#1100000
0%
0$
#1110000
b1 ,
b0 )
b0 *
b0 +
1%
