src/bitorder.sv
`default_nettype none
`timescale 1ns / 1ps

module bitorder(
	input wire clk,
	input wire rst,
	input wire axiiv,
	input wire[1:0] axiid,

	output logic axiov,
	output logic[1:0] axiod
);

logic [7:0] axiod_buffer_1;
logic [7:0] axiod_buffer_2;
logic buffer_switch; // if 0, buffer1 reads in. if 1 buffer2 reads in.
logic[2:0] bit_count; //0th~3rd debit
logic [10:0] byte_count; //how ma:ny bits 
logic [10:0] byte_count_output; //howmany bits are already output
logic old_axiiv;
logic[1:0] rxd_out;
logic[2:0] end_bit_count; //used for the last byte
always_ff @(posedge clk)begin
	if(rst)begin
		axiov <= 0;
		axiod <= 0;
		buffer_switch <= 0;
		bit_count <= 0;
		byte_count <= 0;
		old_axiiv <= 0;
		axiod_buffer_1 <= 0;
		axiod_buffer_2 <= 0;
		end_bit_count <= 0;
		byte_count_output <= 0;
	end
	else if(axiiv)begin
		rxd_out <= axiid;
		if(buffer_switch)
			axiod_buffer_1 <= {axiid,axiod_buffer_1[7:2]};
		else
			axiod_buffer_2 <= {axiid,axiod_buffer_2[7:2]};

		if(bit_count == 3'd3)begin //already read dibits three times
			bit_count <= 3'd4;
			//end_bit_count <= 3'd3;
			byte_count <= byte_count + 1;
			buffer_switch <= ~buffer_switch;
		end else if(bit_count == 3'd4)begin
			bit_count <= 3'd1;
			//end_bit_count <= 3'd0;
		end else begin
			bit_count <= bit_count + 1;
			//end_bit_count <= bit_count;
		end
		if(byte_count >= 1)begin
			axiov <= 1;
			case(bit_count)
				3'd4:begin
					axiod <= buffer_switch ? axiod_buffer_2[7:6] : axiod_buffer_1[7:6];
				end
				3'd1:begin
					axiod <= buffer_switch ? axiod_buffer_2[5:4] : axiod_buffer_1[5:4];
				end
				3'd2:begin
                                        axiod <= buffer_switch ? axiod_buffer_2[3:2] : axiod_buffer_1[3:2];
                                end
				3'd3:begin
                                        axiod <= buffer_switch ? axiod_buffer_2[1:0] : axiod_buffer_1[1:0];
                                end

			endcase
			if(bit_count == 3'd3)begin
				byte_count_output <= byte_count_output + 1;
			end
		end else if(byte_count == 0)begin
			axiov <= 0;
		end
		old_axiiv <= axiiv;
	end else begin
		if(old_axiiv && byte_count_output != byte_count)begin
			/*case(end_bit_count)
                                3'd0:begin
                                        axiod <= buffer_switch ? axiod_buffer_2[7:6] : axiod_buffer_1[7:6];
                                end
                                3'd1:begin
                                        axiod <= buffer_switch ? axiod_buffer_2[5:4] : axiod_buffer_1[5:4];
                                end
                                3'd2:begin
                                        axiod <= buffer_switch ? axiod_buffer_2[3:2] : axiod_buffer_1[3:2];
                                end
                                3'd3:begin
                                        axiod <= buffer_switch ? axiod_buffer_2[1:0] : axiod_buffer_1[1:0];
                                end

                        endcase*/
		        axiov <= 1;
		        case(bit_count)
                                3'd4:begin
                                        axiod <= buffer_switch ? axiod_buffer_2[7:6] : axiod_buffer_1[7:6];
                                end
                                3'd1:begin
                                        axiod <= buffer_switch ? axiod_buffer_2[5:4] : axiod_buffer_1[5:4];
                                end
                                3'd2:begin
                                        axiod <= buffer_switch ? axiod_buffer_2[3:2] : axiod_buffer_1[3:2];
                                end
                                3'd3:begin
                                        axiod <= buffer_switch ? axiod_buffer_2[1:0] : axiod_buffer_1[1:0];
                                end

                        endcase

			/*if(end_bit_count == 3'd3)begin
				//old_axiiv <= 0;
				//bit_count <= 0;
				end_bit_count <= 0;
				//byte_count <= 0;
				//axiov <= 0;
				//bit_count <= 3'd1;
				byte_count_output <= byte_count_output + 1;
			end else begin
				old_axiiv <= 1;
				end_bit_count <= end_bit_count + 1;
				axiov <= 1;
			end*/
		       if(bit_count == 3'd3)begin
			       byte_count_output <= byte_count_output + 1;
			       bit_count <= 3'd4;
		       end else if(bit_count == 3'd4)begin
			       bit_count <= 3'd1;
		       end
		       else begin
			       bit_count <= bit_count + 1;
		       end
		end
		else begin
			old_axiiv <= 0;
			end_bit_count <= 0;
			bit_count <= 0;
			axiov <= 0;
			byte_count <= 0;
			byte_count_output <= 0;
		end
	end
end
endmodule
`default_nettype wire

sim/bitorder_tb.sv

`default_nettype none
`timescale 1ns / 1ps

module bitorder_tb;

logic clk;
logic rst;

logic axiiv;
logic[1:0] axiid;

logic axiov;
logic[1:0] axiod;

bitorder uut(
	.clk(clk),
	.rst(rst),
	.axiiv(axiiv),
	.axiid(axiid),
	.axiov(axiov),
	.axiod(axiod)
);
always begin
	#10;
       	clk = !clk;
end
initial begin
	$dumpfile("bitorder.vcd");
	$dumpvars(0,bitorder_tb);
	$display("Starting Sim");
	clk = 1;
	#20;
	rst = 1;
	#20;
	rst = 0;
	axiid <= 2'b11;
	#10;
	axiiv = 1;

	for(int i = 0;i <4;i = i+1)begin
		if(i < 3)begin
			axiid <= 2'b01;
		end else begin
			axiid <= 2'b11;
		end
		#20;
	end
	#10;
	axiiv = 0;
	#100;
	axiid = 2'b01;;
	axiiv = 1;
	#20;
	axiid = 2'b11;
	#20;
	axiid = 2'b11;
	#20;
	axiid = 2'b11;
	#20;
	for(int i = 0;i < 4;i = i+1)begin
		if(i < 3)begin
                        axiid = 2'b01;
                end else begin
                        axiid = 2'b11;
                end
                #20;
	end
	axiiv = 0;
	#100;
	//test case 2, 0.5 byte
	axiiv = 1;
	for(int i = 0;i<2;i=i+1)begin
		axiid = 2'b01;
		#20;
	end
	axiiv = 0;
	#100;

	//test case 3, 1.5 byte
	axiiv = 1;
	for(int i = 0;i<4;i = i+1)begin
		if(i == 3)begin
			axiid = 2'b01;
		end
		else begin
			axiid = 2'b00;
		end
		#20;
	end
	axiid = 2'b01;
	#20;
	axiid = 2'b00;
	#20
	axiiv = 0;
	#100;
	$display("Finishing Sim");
	$finish;
end
endmodule
`default_nettype wire

bitorder.vcd
$date
	Thu Oct 27 17:45:06 2022
$end
$version
	Icarus Verilog
$end
$timescale
	1ps
$end
$scope module bitorder_tb $end
$var wire 1 ! axiov $end
$var wire 2 " axiod [1:0] $end
$var reg 2 # axiid [1:0] $end
$var reg 1 $ axiiv $end
$var reg 1 % clk $end
$var reg 1 & rst $end
$scope module uut $end
$var wire 2 ' axiid [1:0] $end
$var wire 1 $ axiiv $end
$var wire 1 % clk $end
$var wire 1 & rst $end
$var reg 2 ( axiod [1:0] $end
$var reg 8 ) axiod_buffer_1 [7:0] $end
$var reg 8 * axiod_buffer_2 [7:0] $end
$var reg 1 ! axiov $end
$var reg 3 + bit_count [2:0] $end
$var reg 1 , buffer_switch $end
$var reg 11 - byte_count [10:0] $end
$var reg 11 . byte_count_output [10:0] $end
$var reg 3 / end_bit_count [2:0] $end
$var reg 1 0 old_axiiv $end
$var reg 2 1 rxd_out [1:0] $end
$upscope $end
$scope begin $ivl_for_loop0 $end
$var integer 32 2 i [31:0] $end
$upscope $end
$scope begin $ivl_for_loop1 $end
$var integer 32 3 i [31:0] $end
$upscope $end
$scope begin $ivl_for_loop2 $end
$var integer 32 4 i [31:0] $end
$upscope $end
$scope begin $ivl_for_loop3 $end
$var integer 32 5 i [31:0] $end
$upscope $end
$upscope $end
$enddefinitions $end
#0
$dumpvars
b0 5
b0 4
b0 3
b0 2
bx 1
00
b0 /
b0 .
b0 -
x,
b0 +
bx *
bx )
bx (
bx '
x&
1%
x$
bx #
bx "
0!
$end
#10000
0%
#20000
b0 *
b0 )
0,
b0 "
b0 (
1%
1&
#30000
0%
#40000
b11 #
b11 '
1%
0&
#50000
b1 #
b1 '
0%
1$
#60000
10
b1 +
b1000000 *
b1 1
1%
#70000
0%
b1 2
#80000
b10 +
b1010000 *
1%
#90000
0%
b10 2
#100000
b11 +
b1010100 *
1%
#110000
b11 #
b11 '
0%
b11 2
#120000
1,
b1 -
b100 +
b11010101 *
b11 1
1%
#130000
0%
b100 2
#140000
b1 +
b11 "
b11 (
1!
1%
0$
#150000
0%
#160000
b10 +
b1 "
b1 (
1%
#170000
0%
#180000
b11 +
1%
#190000
0%
#200000
b100 +
b1 .
1%
#210000
0%
#220000
b0 .
b0 -
0!
b0 +
00
1%
#230000
0%
#240000
10
b1 +
b1000000 )
b1 1
1%
1$
b1 #
b1 '
#250000
0%
#260000
b10 +
b11010000 )
b11 1
1%
b11 #
b11 '
#270000
0%
#280000
b11 +
b11110100 )
1%
#290000
0%
#300000
0,
b1 -
b100 +
b11111101 )
1%
#310000
0%
#320000
b11 "
b11 (
1!
b1 +
b1110101 *
b1 1
1%
b1 #
b1 '
#330000
0%
#340000
b10 +
b1011101 *
1%
b1 3
#350000
0%
#360000
b11 +
b1010111 *
1%
b10 3
#370000
0%
#380000
b1 .
b1 "
b1 (
1,
b10 -
b100 +
b11010101 *
b11 1
1%
b11 #
b11 '
b11 3
#390000
0%
#400000
b1 +
b11 "
b11 (
1%
0$
b100 3
#410000
0%
#420000
b10 +
b1 "
b1 (
1%
#430000
0%
#440000
b11 +
1%
#450000
0%
#460000
b100 +
b10 .
1%
#470000
0%
#480000
b0 .
b0 -
0!
b0 +
00
1%
#490000
0%
#500000
10
b1 +
b1111111 )
b1 1
1%
b1 #
b1 '
1$
#510000
0%
#520000
b10 +
b1011111 )
1%
b1 4
#530000
0%
#540000
b0 +
00
1%
0$
b10 4
#550000
0%
#560000
1%
#570000
0%
#580000
1%
#590000
0%
#600000
1%
#610000
0%
#620000
1%
#630000
0%
#640000
10
b1 +
b10111 )
b0 1
1%
b0 #
b0 '
1$
#650000
0%
#660000
b10 +
b101 )
1%
b1 5
#670000
0%
#680000
b11 +
b1 )
1%
b10 5
#690000
0%
#700000
0,
b1 -
b100 +
b1000000 )
b1 1
1%
b1 #
b1 '
b11 5
#710000
0%
#720000
1!
b1 +
b1110101 *
1%
b100 5
#730000
0%
#740000
b0 "
b0 (
b10 +
b11101 *
b0 1
1%
b0 #
b0 '
#750000
0%
#760000
b11 +
1%
0$
#770000
0%
#780000
b100 +
b1 .
1%
#790000
0%
#800000
b0 .
b0 -
0!
b0 +
00
1%
