src/bitorder.sv
`default_nettype none
`timescale 1ns / 1ps

module bitorder(
	input wire clk,
	input wire rst,
	input wire axiiv,
	input wire[1:0] axiid,

	output logic axiov,
	output logic[1:0] axiod
);

logic [7:0] axiod_buffer_1;
logic [7:0] axiod_buffer_2;
logic buffer_switch; // if 0, buffer1 reads in. if 1 buffer2 reads in.
logic[1:0] bit_count; //0th~3rd debit
logic [10:0] byte_count; //how many bits 
logic old_axiiv;
always_ff @(posedge clk)begin
	if(rst)begin
		axiov <= 0;
		axiod <= 0;
		buffer_switch <= 0;
		bit_count <= 0;
		byte_count <= 0;
	end
	else if(axiiv)begin
		if(buffer_switch)
			axiod_buffer_1 <= {axiid,axiod_buffer_1[7:2]};
		else
			axiod_buffer_2 <= {axiid,axiod_buffer_2[7:2]};

		if(bit_count == 2'b11)begin //already read dibits three times
			bit_count <= 2'b00;
			byte_count = byte_count + 1;
			buffer_switch <= ~buffer_switch;
		end else begin
			bit_count <= bit_count + 1;
		end
		if(byte_count >= 1)begin
			axiov <= 1;
			case(bit_count)
				2'b00:begin
					axiod <= buffer_switch ? axiod_buffer_2[7:6] : axiod_buffer_1[7:6];
				end
				2'b01:begin
					axiod <= buffer_switch ? axiod_buffer_2[5:4] : axiod_buffer_1[5:4];
				end
				2'b10:begin
                                        axiod <= buffer_switch ? axiod_buffer_2[3:2] : axiod_buffer_1[3:2];
                                end
				2'b11:begin
                                        axiod <= buffer_switch ? axiod_buffer_2[1:0] : axiod_buffer_1[1:0];
                                end

			endcase
		end else if(byte_count == 0)begin
			axiov <= 0;
		end
		old_axiiv <= axiiv;
	end else begin
		if(old_axiiv)begin
			case(bit_count)
                                2'b00:begin
                                        axiod <= buffer_switch ? axiod_buffer_2[7:6] : axiod_buffer_1[7:6];
                                end
                                2'b01:begin
                                        axiod <= buffer_switch ? axiod_buffer_2[5:4] : axiod_buffer_1[5:4];
                                end
                                2'b10:begin
                                        axiod <= buffer_switch ? axiod_buffer_2[3:2] : axiod_buffer_1[3:2];
                                end
                                2'b11:begin
                                        axiod <= buffer_switch ? axiod_buffer_2[1:0] : axiod_buffer_1[1:0];
                                end

                        endcase
			if(bit_count == 2'b11)begin
				old_axiiv <= 0;
				bit_count <= 0;
			end else begin
				old_axiiv <= 1;
				bit_count = bit_count + 1;
			end
		end
		axiov <= 0;
	end
end
endmodule
`default_nettype wire

sim/bitorder_tb.sv

`default_nettype none
`timescale 1ns / 1ps

module bitorder_tb;

logic clk;
logic rst;

logic axiiv;
logic[1:0] axiid;

logic axiov;
logic[1:0] axiod;

bitorder uut(
	.clk(clk),
	.rst(rst),
	.axiiv(axiiv),
	.axiid(axiid),
	.axiov(axiov),
	.axiod(axiod)
);
always begin
	#10;
       	clk = !clk;
end
initial begin
	$dumpfile("bitorder.vcd");
	$dumpvars(0,bitorder_tb);
	$display("Starting Sim");
	clk = 0;
	#20;
	rst = 1;
	#20;
	rst = 0;
	axiiv = 1;
	#10;

	for(int i = 0;i <4;i = i+1)begin
		if(i < 3)begin
			axiid <= 2'b01;
		end else begin
			axiid <= 2'b11;
		end
		#20;
	end
	axiiv = 0;
	#100;
	//test case 1, 1 byte
	$display("Finishing Sim");
	$finish;
end
endmodule
`default_nettype wire

bitorder.vcd
$date
	Wed Oct 26 22:04:58 2022
$end
$version
	Icarus Verilog
$end
$timescale
	1ps
$end
$scope module bitorder_tb $end
$var wire 1 ! axiov $end
$var wire 2 " axiod [1:0] $end
$var reg 2 # axiid [1:0] $end
$var reg 1 $ axiiv $end
$var reg 1 % clk $end
$var reg 1 & rst $end
$scope module uut $end
$var wire 2 ' axiid [1:0] $end
$var wire 1 $ axiiv $end
$var wire 1 % clk $end
$var wire 1 & rst $end
$var reg 2 ( axiod [1:0] $end
$var reg 8 ) axiod_buffer_1 [7:0] $end
$var reg 8 * axiod_buffer_2 [7:0] $end
$var reg 1 ! axiov $end
$var reg 2 + bit_count [1:0] $end
$var reg 1 , buffer_switch $end
$var reg 11 - byte_count [10:0] $end
$var reg 1 . old_axiiv $end
$upscope $end
$scope begin $ivl_for_loop0 $end
$var integer 32 / i [31:0] $end
$upscope $end
$upscope $end
$enddefinitions $end
#0
$dumpvars
b0 /
x.
bx -
x,
bx +
bx *
bx )
bx (
bx '
x&
0%
x$
bx #
bx "
x!
$end
#10000
0!
1%
#20000
0%
1&
#30000
b0 -
b0 +
0,
b0 "
b0 (
1%
#40000
0%
1$
0&
#50000
1.
b1 +
b1 #
b1 '
1%
#60000
0%
#70000
b10 +
b1xxxxxx *
1%
b1 /
#80000
0%
#90000
b11 +
b101xxxx *
1%
b10 /
#100000
0%
#110000
bx "
bx (
1!
1,
b0 +
b10101xx *
b11 #
b11 '
b1 -
1%
b11 /
#120000
0%
#130000
0!
b1 "
b1 (
b1 +
1%
0$
b100 /
#140000
0%
#150000
b10 +
1%
#160000
0%
#170000
b11 +
1%
#180000
0%
#190000
b0 +
0.
bx "
bx (
1%
