src/ether.sv
`default_nettype none
`timescale 1ns / 1ps

module ether(
	input wire clk,
	input wire rst,
	input wire [1:0] rxd,
	input wire crsdv,

	output logic axiov,
	output logic [1:0] axiod
);


logic[3:0] now_state;
logic [5:0] rxd_count;
logic [2:0] sfd_count;
/*
* 0000: ready state
* 0001: validating preamble
* 0010: validating SFD
* 0100: reading data
*/
always_ff @(posedge clk)begin
	if(rst)begin
		rxd_count <= 0;
		sfd_count <= 0;
		axiov <= 0;
		axiod <= 2'b00; //reset?
		now_state <= 4'b0000;
	end
	else begin
		if(crsdv)begin
			case(now_state)
				4'b0000:begin
					if(rxd == 2'b01)begin
						//shift to preamble validation
						now_state <= 4'b0001;
						rxd_count <= 1;
					end
				end
				4'b0001:begin
					if(rxd == 2'b01)begin
						if(rxd_count == 6'd55)begin
							//preamble validating done
							rxd_count <= 0;
							now_state <= 4'b0010;
						end else begin
							//still validating
							rxd_count <= rxd_count + 1;
						end
					end else begin
						//invalid, back to ready state
						rxd_count <= 0;
						now_state <= 4'b0000;
					end
				end
				4'b0010:begin
					//validate sfd
					if(sfd_count < 3)begin
						if(rxd == 2'b01)begin
							//still validating
							sfd_count <= sfd_count + 1;
						end else begin
							//invalid, back to ready state
							sfd_count <= 0;
							now_state <= 4'b0000;
						end
					end else if(sfd_count == 3)begin
						if(rxd == 2'b11)begin
							//sfd check done, start reading
							sfd_count <= 0;
							now_state <= 4'b0100;
						end else begin
							//invalid, back to ready state
							sfd_count <= 0;
							now_state <= 4'b0000;
						end
					end
				end
				4'b0100:begin
					if(crsdv)begin
						//not finished reading, read more
						axiov <= 1;
						axiod <= rxd;
					end else begin
						//end of packet, back to ready state
						axiov <= 0;
						axiod <= 2'b00;
						now_state <= 4'b0000;
					end
				end
			endcase
		end else begin
			//same as reset
			rxd_count <= 0;
                	sfd_count <= 0;
                	axiov <= 0;
                	axiod <= 2'b00; //reset?
                	now_state <= 4'b0000;
		end
	end


end
endmodule
`default_nettype wire

sim/ether_tb.sv
`default_nettype none
`timescale 1ns / 1ps

module ether_tb;

logic clk;
logic rst;

logic [1:0] rxd;
logic crsdv;

logic [1:0] axiod;
logic axiov;

logic [47:0] addr_d,addr_s;
logic [15:0] length;
logic [15:0] data;
logic [31:0] fcs;
ether uut(
	.clk(clk),
	.rst(rst),
	.rxd(rxd),
	.crsdv(crsdv),
	.axiov(axiov),
	.axiod(axiod));

always begin
	#10;
       	clk = !clk;
end

initial begin
	$dumpfile("ether.vcd");
	$dumpvars(0,ether_tb);
	$display("Starting Sim");
	clk = 0;
	#20;
	rst = 1;
	#10;
	rst = 0;
	crsdv = 1;
	//test case 1: valid packet
	//valid preamble
	for(int i = 0;i<56;i=i+1)begin
		rxd = 2'b01;
		#20;
	end
	//valid sfd
	for(int i = 0;i<4;i = i+1)begin
		if(i < 3)begin
			rxd = 2'b01;
		end else begin
			rxd = 2'b11;
		end
		#20;
	end
	//D.A.
	for(int i = 0;i < 48;i=i+1)begin
		rxd = 2'b11;
		#20;
	end
	//S.A.
	for(int i = 0;i <48;i=i+1)begin
		rxd = 2'b11;
		#20;
	end
	//Data
	for(int i = 0;i < 16;i = i+1)begin
		rxd = 2'b10;
		#20;
	end
	//FCS
	for(int i = 0;i < 16;i = i+1)begin
		rxd = 2'b11;
		#20;
	end
	crsdv = 0;
	#20;
	crsdv = 1;
	#20;
	//test case 2: invalid preamble
	//invalid preamble
        for(int i = 0;i<56;i=i+1)begin
		if(i == 20)begin
			rxd = 2'b10;
		end else begin
			rxd = 2'b01;
		end
                #20;
        end
        //valid sfd
        for(int i = 0;i<4;i = i+1)begin
                if(i < 3)begin
                        rxd = 2'b01;
                end else begin
                        rxd = 2'b11;
                end
                #20;
        end
        //D.A.
        for(int i = 0;i < 48;i=i+1)begin
                rxd = 2'b11;
                #20;
        end
        //S.A.
        for(int i = 0;i <48;i=i+1)begin
                rxd = 2'b11;
                #20;
        end
        //Data
        for(int i = 0;i < 16;i = i+1)begin
                rxd = 2'b10;
                #20;
        end
        //FCS
        for(int i = 0;i < 16;i = i+1)begin
                rxd = 2'b11;
                #20;
        end
        crsdv = 0;
        #20;
	crsdv = 1;
	#20;
	//test case 3: valid preamble, tiny message(2 bits)
	//preamble
        for(int i = 0;i<56;i=i+1)begin
		rxd = 2'b01;
                #20;
        end
        //valid sfd
        for(int i = 0;i<4;i = i+1)begin
		if(i<3)begin
			rxd = 2'b01;
		end else begin
			rxd = 2'b11;
		end
                #20;
        end
	//only two bits
	rxd = 2'b01;
	#20;
	rxd = 2'b01;
	#20;
        crsdv = 0;
        #100;

	crsdv = 1;
	#20;
        //test case 3 :invalid sfd
        //invalid preamble
        for(int i = 0;i<56;i=i+1)begin
                rxd = 2'b01;
                #20;
        end
        //valid sfd
        for(int i = 0;i<4;i = i+1)begin
		if(i < 3)begin
			rxd = 2'b01;
		end else begin
			rxd = 2'b11;
		end
                #20;
        end
        //D.A.
        for(int i = 0;i < 48;i=i+1)begin
                rxd = 2'b11;
                #20;
        end
        //S.A.
        for(int i = 0;i <48;i=i+1)begin
                rxd = 2'b11;
                #20;
        end
        //Data
        for(int i = 0;i < 16;i = i+1)begin
                rxd = 2'b10;
                #20;
        end
        //FCS
        for(int i = 0;i < 16;i = i+1)begin
                rxd = 2'b11;
                #20;
        end
        crsdv = 0;
        #100;

	$display("Finishing Sim");
	$finish;
end
endmodule

`default_nettype wire

ether.vcd
$date
	Wed Oct 26 17:15:40 2022
$end
$version
	Icarus Verilog
$end
$timescale
	1ps
$end
$scope module ether_tb $end
$var wire 1 ! axiov $end
$var wire 2 " axiod [1:0] $end
$var reg 1 # clk $end
$var reg 1 $ crsdv $end
$var reg 1 % rst $end
$var reg 2 & rxd [1:0] $end
$scope module uut $end
$var wire 1 # clk $end
$var wire 1 $ crsdv $end
$var wire 1 % rst $end
$var wire 2 ' rxd [1:0] $end
$var reg 2 ( axiod [1:0] $end
$var reg 1 ! axiov $end
$var reg 4 ) now_state [3:0] $end
$var reg 6 * rxd_count [5:0] $end
$var reg 3 + sfd_count [2:0] $end
$upscope $end
$scope begin $ivl_for_loop0 $end
$var integer 32 , i [31:0] $end
$upscope $end
$scope begin $ivl_for_loop1 $end
$var integer 32 - i [31:0] $end
$upscope $end
$scope begin $ivl_for_loop10 $end
$var integer 32 . i [31:0] $end
$upscope $end
$scope begin $ivl_for_loop11 $end
$var integer 32 / i [31:0] $end
$upscope $end
$scope begin $ivl_for_loop12 $end
$var integer 32 0 i [31:0] $end
$upscope $end
$scope begin $ivl_for_loop13 $end
$var integer 32 1 i [31:0] $end
$upscope $end
$scope begin $ivl_for_loop14 $end
$var integer 32 2 i [31:0] $end
$upscope $end
$scope begin $ivl_for_loop15 $end
$var integer 32 3 i [31:0] $end
$upscope $end
$scope begin $ivl_for_loop16 $end
$var integer 32 4 i [31:0] $end
$upscope $end
$scope begin $ivl_for_loop17 $end
$var integer 32 5 i [31:0] $end
$upscope $end
$scope begin $ivl_for_loop18 $end
$var integer 32 6 i [31:0] $end
$upscope $end
$scope begin $ivl_for_loop19 $end
$var integer 32 7 i [31:0] $end
$upscope $end
$scope begin $ivl_for_loop2 $end
$var integer 32 8 i [31:0] $end
$upscope $end
$scope begin $ivl_for_loop3 $end
$var integer 32 9 i [31:0] $end
$upscope $end
$scope begin $ivl_for_loop4 $end
$var integer 32 : i [31:0] $end
$upscope $end
$scope begin $ivl_for_loop5 $end
$var integer 32 ; i [31:0] $end
$upscope $end
$scope begin $ivl_for_loop6 $end
$var integer 32 < i [31:0] $end
$upscope $end
$scope begin $ivl_for_loop7 $end
$var integer 32 = i [31:0] $end
$upscope $end
$scope begin $ivl_for_loop8 $end
$var integer 32 > i [31:0] $end
$upscope $end
$scope begin $ivl_for_loop9 $end
$var integer 32 ? i [31:0] $end
$upscope $end
$upscope $end
$enddefinitions $end
#0
$dumpvars
b0 ?
b0 >
b0 =
b0 <
b0 ;
b0 :
b0 9
b0 8
b0 7
b0 6
b0 5
b0 4
b0 3
b0 2
b0 1
b0 0
b0 /
b0 .
b0 -
b0 ,
bx +
bx *
bx )
bx (
bx '
bx &
x%
x$
0#
bx "
x!
$end
#10000
b0 )
b0 "
b0 (
0!
b0 +
b0 *
1#
#20000
0#
1%
#30000
b1 *
b1 )
1#
b1 &
b1 '
1$
0%
#40000
0#
#50000
b10 *
1#
b1 ,
#60000
0#
#70000
b11 *
1#
b10 ,
#80000
0#
#90000
b100 *
1#
b11 ,
#100000
0#
#110000
b101 *
1#
b100 ,
#120000
0#
#130000
b110 *
1#
b101 ,
#140000
0#
#150000
b111 *
1#
b110 ,
#160000
0#
#170000
b1000 *
1#
b111 ,
#180000
0#
#190000
b1001 *
1#
b1000 ,
#200000
0#
#210000
b1010 *
1#
b1001 ,
#220000
0#
#230000
b1011 *
1#
b1010 ,
#240000
0#
#250000
b1100 *
1#
b1011 ,
#260000
0#
#270000
b1101 *
1#
b1100 ,
#280000
0#
#290000
b1110 *
1#
b1101 ,
#300000
0#
#310000
b1111 *
1#
b1110 ,
#320000
0#
#330000
b10000 *
1#
b1111 ,
#340000
0#
#350000
b10001 *
1#
b10000 ,
#360000
0#
#370000
b10010 *
1#
b10001 ,
#380000
0#
#390000
b10011 *
1#
b10010 ,
#400000
0#
#410000
b10100 *
1#
b10011 ,
#420000
0#
#430000
b10101 *
1#
b10100 ,
#440000
0#
#450000
b10110 *
1#
b10101 ,
#460000
0#
#470000
b10111 *
1#
b10110 ,
#480000
0#
#490000
b11000 *
1#
b10111 ,
#500000
0#
#510000
b11001 *
1#
b11000 ,
#520000
0#
#530000
b11010 *
1#
b11001 ,
#540000
0#
#550000
b11011 *
1#
b11010 ,
#560000
0#
#570000
b11100 *
1#
b11011 ,
#580000
0#
#590000
b11101 *
1#
b11100 ,
#600000
0#
#610000
b11110 *
1#
b11101 ,
#620000
0#
#630000
b11111 *
1#
b11110 ,
#640000
0#
#650000
b100000 *
1#
b11111 ,
#660000
0#
#670000
b100001 *
1#
b100000 ,
#680000
0#
#690000
b100010 *
1#
b100001 ,
#700000
0#
#710000
b100011 *
1#
b100010 ,
#720000
0#
#730000
b100100 *
1#
b100011 ,
#740000
0#
#750000
b100101 *
1#
b100100 ,
#760000
0#
#770000
b100110 *
1#
b100101 ,
#780000
0#
#790000
b100111 *
1#
b100110 ,
#800000
0#
#810000
b101000 *
1#
b100111 ,
#820000
0#
#830000
b101001 *
1#
b101000 ,
#840000
0#
#850000
b101010 *
1#
b101001 ,
#860000
0#
#870000
b101011 *
1#
b101010 ,
#880000
0#
#890000
b101100 *
1#
b101011 ,
#900000
0#
#910000
b101101 *
1#
b101100 ,
#920000
0#
#930000
b101110 *
1#
b101101 ,
#940000
0#
#950000
b101111 *
1#
b101110 ,
#960000
0#
#970000
b110000 *
1#
b101111 ,
#980000
0#
#990000
b110001 *
1#
b110000 ,
#1000000
0#
#1010000
b110010 *
1#
b110001 ,
#1020000
0#
#1030000
b110011 *
1#
b110010 ,
#1040000
0#
#1050000
b110100 *
1#
b110011 ,
#1060000
0#
#1070000
b110101 *
1#
b110100 ,
#1080000
0#
#1090000
b110110 *
1#
b110101 ,
#1100000
0#
#1110000
b110111 *
1#
b110110 ,
#1120000
0#
#1130000
b10 )
b0 *
1#
b110111 ,
#1140000
0#
#1150000
b1 +
1#
b111000 ,
#1160000
0#
#1170000
b10 +
1#
b1 -
#1180000
0#
#1190000
b11 +
1#
b10 -
#1200000
0#
#1210000
b100 )
b0 +
1#
b11 &
b11 '
b11 -
#1220000
0#
#1230000
b11 "
b11 (
1!
1#
b100 -
#1240000
0#
#1250000
1#
b1 8
#1260000
0#
#1270000
1#
b10 8
#1280000
0#
#1290000
1#
b11 8
#1300000
0#
#1310000
1#
b100 8
#1320000
0#
#1330000
1#
b101 8
#1340000
0#
#1350000
1#
b110 8
#1360000
0#
#1370000
1#
b111 8
#1380000
0#
#1390000
1#
b1000 8
#1400000
0#
#1410000
1#
b1001 8
#1420000
0#
#1430000
1#
b1010 8
#1440000
0#
#1450000
1#
b1011 8
#1460000
0#
#1470000
1#
b1100 8
#1480000
0#
#1490000
1#
b1101 8
#1500000
0#
#1510000
1#
b1110 8
#1520000
0#
#1530000
1#
b1111 8
#1540000
0#
#1550000
1#
b10000 8
#1560000
0#
#1570000
1#
b10001 8
#1580000
0#
#1590000
1#
b10010 8
#1600000
0#
#1610000
1#
b10011 8
#1620000
0#
#1630000
1#
b10100 8
#1640000
0#
#1650000
1#
b10101 8
#1660000
0#
#1670000
1#
b10110 8
#1680000
0#
#1690000
1#
b10111 8
#1700000
0#
#1710000
1#
b11000 8
#1720000
0#
#1730000
1#
b11001 8
#1740000
0#
#1750000
1#
b11010 8
#1760000
0#
#1770000
1#
b11011 8
#1780000
0#
#1790000
1#
b11100 8
#1800000
0#
#1810000
1#
b11101 8
#1820000
0#
#1830000
1#
b11110 8
#1840000
0#
#1850000
1#
b11111 8
#1860000
0#
#1870000
1#
b100000 8
#1880000
0#
#1890000
1#
b100001 8
#1900000
0#
#1910000
1#
b100010 8
#1920000
0#
#1930000
1#
b100011 8
#1940000
0#
#1950000
1#
b100100 8
#1960000
0#
#1970000
1#
b100101 8
#1980000
0#
#1990000
1#
b100110 8
#2000000
0#
#2010000
1#
b100111 8
#2020000
0#
#2030000
1#
b101000 8
#2040000
0#
#2050000
1#
b101001 8
#2060000
0#
#2070000
1#
b101010 8
#2080000
0#
#2090000
1#
b101011 8
#2100000
0#
#2110000
1#
b101100 8
#2120000
0#
#2130000
1#
b101101 8
#2140000
0#
#2150000
1#
b101110 8
#2160000
0#
#2170000
1#
b101111 8
#2180000
0#
#2190000
1#
b110000 8
#2200000
0#
#2210000
1#
b1 9
#2220000
0#
#2230000
1#
b10 9
#2240000
0#
#2250000
1#
b11 9
#2260000
0#
#2270000
1#
b100 9
#2280000
0#
#2290000
1#
b101 9
#2300000
0#
#2310000
1#
b110 9
#2320000
0#
#2330000
1#
b111 9
#2340000
0#
#2350000
1#
b1000 9
#2360000
0#
#2370000
1#
b1001 9
#2380000
0#
#2390000
1#
b1010 9
#2400000
0#
#2410000
1#
b1011 9
#2420000
0#
#2430000
1#
b1100 9
#2440000
0#
#2450000
1#
b1101 9
#2460000
0#
#2470000
1#
b1110 9
#2480000
0#
#2490000
1#
b1111 9
#2500000
0#
#2510000
1#
b10000 9
#2520000
0#
#2530000
1#
b10001 9
#2540000
0#
#2550000
1#
b10010 9
#2560000
0#
#2570000
1#
b10011 9
#2580000
0#
#2590000
1#
b10100 9
#2600000
0#
#2610000
1#
b10101 9
#2620000
0#
#2630000
1#
b10110 9
#2640000
0#
#2650000
1#
b10111 9
#2660000
0#
#2670000
1#
b11000 9
#2680000
0#
#2690000
1#
b11001 9
#2700000
0#
#2710000
1#
b11010 9
#2720000
0#
#2730000
1#
b11011 9
#2740000
0#
#2750000
1#
b11100 9
#2760000
0#
#2770000
1#
b11101 9
#2780000
0#
#2790000
1#
b11110 9
#2800000
0#
#2810000
1#
b11111 9
#2820000
0#
#2830000
1#
b100000 9
#2840000
0#
#2850000
1#
b100001 9
#2860000
0#
#2870000
1#
b100010 9
#2880000
0#
#2890000
1#
b100011 9
#2900000
0#
#2910000
1#
b100100 9
#2920000
0#
#2930000
1#
b100101 9
#2940000
0#
#2950000
1#
b100110 9
#2960000
0#
#2970000
1#
b100111 9
#2980000
0#
#2990000
1#
b101000 9
#3000000
0#
#3010000
1#
b101001 9
#3020000
0#
#3030000
1#
b101010 9
#3040000
0#
#3050000
1#
b101011 9
#3060000
0#
#3070000
1#
b101100 9
#3080000
0#
#3090000
1#
b101101 9
#3100000
0#
#3110000
1#
b101110 9
#3120000
0#
#3130000
1#
b101111 9
#3140000
0#
#3150000
b10 "
b10 (
1#
b10 &
b10 '
b110000 9
#3160000
0#
#3170000
1#
b1 :
#3180000
0#
#3190000
1#
b10 :
#3200000
0#
#3210000
1#
b11 :
#3220000
0#
#3230000
1#
b100 :
#3240000
0#
#3250000
1#
b101 :
#3260000
0#
#3270000
1#
b110 :
#3280000
0#
#3290000
1#
b111 :
#3300000
0#
#3310000
1#
b1000 :
#3320000
0#
#3330000
1#
b1001 :
#3340000
0#
#3350000
1#
b1010 :
#3360000
0#
#3370000
1#
b1011 :
#3380000
0#
#3390000
1#
b1100 :
#3400000
0#
#3410000
1#
b1101 :
#3420000
0#
#3430000
1#
b1110 :
#3440000
0#
#3450000
1#
b1111 :
#3460000
0#
#3470000
b11 "
b11 (
1#
b11 &
b11 '
b10000 :
#3480000
0#
#3490000
1#
b1 ;
#3500000
0#
#3510000
1#
b10 ;
#3520000
0#
#3530000
1#
b11 ;
#3540000
0#
#3550000
1#
b100 ;
#3560000
0#
#3570000
1#
b101 ;
#3580000
0#
#3590000
1#
b110 ;
#3600000
0#
#3610000
1#
b111 ;
#3620000
0#
#3630000
1#
b1000 ;
#3640000
0#
#3650000
1#
b1001 ;
#3660000
0#
#3670000
1#
b1010 ;
#3680000
0#
#3690000
1#
b1011 ;
#3700000
0#
#3710000
1#
b1100 ;
#3720000
0#
#3730000
1#
b1101 ;
#3740000
0#
#3750000
1#
b1110 ;
#3760000
0#
#3770000
1#
b1111 ;
#3780000
0#
#3790000
b0 )
b0 "
b0 (
0!
1#
0$
b10000 ;
#3800000
0#
#3810000
1#
1$
#3820000
0#
#3830000
b1 *
b1 )
1#
b1 &
b1 '
#3840000
0#
#3850000
b10 *
1#
b1 <
#3860000
0#
#3870000
b11 *
1#
b10 <
#3880000
0#
#3890000
b100 *
1#
b11 <
#3900000
0#
#3910000
b101 *
1#
b100 <
#3920000
0#
#3930000
b110 *
1#
b101 <
#3940000
0#
#3950000
b111 *
1#
b110 <
#3960000
0#
#3970000
b1000 *
1#
b111 <
#3980000
0#
#3990000
b1001 *
1#
b1000 <
#4000000
0#
#4010000
b1010 *
1#
b1001 <
#4020000
0#
#4030000
b1011 *
1#
b1010 <
#4040000
0#
#4050000
b1100 *
1#
b1011 <
#4060000
0#
#4070000
b1101 *
1#
b1100 <
#4080000
0#
#4090000
b1110 *
1#
b1101 <
#4100000
0#
#4110000
b1111 *
1#
b1110 <
#4120000
0#
#4130000
b10000 *
1#
b1111 <
#4140000
0#
#4150000
b10001 *
1#
b10000 <
#4160000
0#
#4170000
b10010 *
1#
b10001 <
#4180000
0#
#4190000
b10011 *
1#
b10010 <
#4200000
0#
#4210000
b10100 *
1#
b10011 <
#4220000
0#
#4230000
b0 )
b0 *
1#
b10 &
b10 '
b10100 <
#4240000
0#
#4250000
b1 *
b1 )
1#
b1 &
b1 '
b10101 <
#4260000
0#
#4270000
b10 *
1#
b10110 <
#4280000
0#
#4290000
b11 *
1#
b10111 <
#4300000
0#
#4310000
b100 *
1#
b11000 <
#4320000
0#
#4330000
b101 *
1#
b11001 <
#4340000
0#
#4350000
b110 *
1#
b11010 <
#4360000
0#
#4370000
b111 *
1#
b11011 <
#4380000
0#
#4390000
b1000 *
1#
b11100 <
#4400000
0#
#4410000
b1001 *
1#
b11101 <
#4420000
0#
#4430000
b1010 *
1#
b11110 <
#4440000
0#
#4450000
b1011 *
1#
b11111 <
#4460000
0#
#4470000
b1100 *
1#
b100000 <
#4480000
0#
#4490000
b1101 *
1#
b100001 <
#4500000
0#
#4510000
b1110 *
1#
b100010 <
#4520000
0#
#4530000
b1111 *
1#
b100011 <
#4540000
0#
#4550000
b10000 *
1#
b100100 <
#4560000
0#
#4570000
b10001 *
1#
b100101 <
#4580000
0#
#4590000
b10010 *
1#
b100110 <
#4600000
0#
#4610000
b10011 *
1#
b100111 <
#4620000
0#
#4630000
b10100 *
1#
b101000 <
#4640000
0#
#4650000
b10101 *
1#
b101001 <
#4660000
0#
#4670000
b10110 *
1#
b101010 <
#4680000
0#
#4690000
b10111 *
1#
b101011 <
#4700000
0#
#4710000
b11000 *
1#
b101100 <
#4720000
0#
#4730000
b11001 *
1#
b101101 <
#4740000
0#
#4750000
b11010 *
1#
b101110 <
#4760000
0#
#4770000
b11011 *
1#
b101111 <
#4780000
0#
#4790000
b11100 *
1#
b110000 <
#4800000
0#
#4810000
b11101 *
1#
b110001 <
#4820000
0#
#4830000
b11110 *
1#
b110010 <
#4840000
0#
#4850000
b11111 *
1#
b110011 <
#4860000
0#
#4870000
b100000 *
1#
b110100 <
#4880000
0#
#4890000
b100001 *
1#
b110101 <
#4900000
0#
#4910000
b100010 *
1#
b110110 <
#4920000
0#
#4930000
b100011 *
1#
b110111 <
#4940000
0#
#4950000
b100100 *
1#
b111000 <
#4960000
0#
#4970000
b100101 *
1#
b1 =
#4980000
0#
#4990000
b100110 *
1#
b10 =
#5000000
0#
#5010000
b0 )
b0 *
1#
b11 &
b11 '
b11 =
#5020000
0#
#5030000
1#
b100 =
#5040000
0#
#5050000
1#
b1 >
#5060000
0#
#5070000
1#
b10 >
#5080000
0#
#5090000
1#
b11 >
#5100000
0#
#5110000
1#
b100 >
#5120000
0#
#5130000
1#
b101 >
#5140000
0#
#5150000
1#
b110 >
#5160000
0#
#5170000
1#
b111 >
#5180000
0#
#5190000
1#
b1000 >
#5200000
0#
#5210000
1#
b1001 >
#5220000
0#
#5230000
1#
b1010 >
#5240000
0#
#5250000
1#
b1011 >
#5260000
0#
#5270000
1#
b1100 >
#5280000
0#
#5290000
1#
b1101 >
#5300000
0#
#5310000
1#
b1110 >
#5320000
0#
#5330000
1#
b1111 >
#5340000
0#
#5350000
1#
b10000 >
#5360000
0#
#5370000
1#
b10001 >
#5380000
0#
#5390000
1#
b10010 >
#5400000
0#
#5410000
1#
b10011 >
#5420000
0#
#5430000
1#
b10100 >
#5440000
0#
#5450000
1#
b10101 >
#5460000
0#
#5470000
1#
b10110 >
#5480000
0#
#5490000
1#
b10111 >
#5500000
0#
#5510000
1#
b11000 >
#5520000
0#
#5530000
1#
b11001 >
#5540000
0#
#5550000
1#
b11010 >
#5560000
0#
#5570000
1#
b11011 >
#5580000
0#
#5590000
1#
b11100 >
#5600000
0#
#5610000
1#
b11101 >
#5620000
0#
#5630000
1#
b11110 >
#5640000
0#
#5650000
1#
b11111 >
#5660000
0#
#5670000
1#
b100000 >
#5680000
0#
#5690000
1#
b100001 >
#5700000
0#
#5710000
1#
b100010 >
#5720000
0#
#5730000
1#
b100011 >
#5740000
0#
#5750000
1#
b100100 >
#5760000
0#
#5770000
1#
b100101 >
#5780000
0#
#5790000
1#
b100110 >
#5800000
0#
#5810000
1#
b100111 >
#5820000
0#
#5830000
1#
b101000 >
#5840000
0#
#5850000
1#
b101001 >
#5860000
0#
#5870000
1#
b101010 >
#5880000
0#
#5890000
1#
b101011 >
#5900000
0#
#5910000
1#
b101100 >
#5920000
0#
#5930000
1#
b101101 >
#5940000
0#
#5950000
1#
b101110 >
#5960000
0#
#5970000
1#
b101111 >
#5980000
0#
#5990000
1#
b110000 >
#6000000
0#
#6010000
1#
b1 ?
#6020000
0#
#6030000
1#
b10 ?
#6040000
0#
#6050000
1#
b11 ?
#6060000
0#
#6070000
1#
b100 ?
#6080000
0#
#6090000
1#
b101 ?
#6100000
0#
#6110000
1#
b110 ?
#6120000
0#
#6130000
1#
b111 ?
#6140000
0#
#6150000
1#
b1000 ?
#6160000
0#
#6170000
1#
b1001 ?
#6180000
0#
#6190000
1#
b1010 ?
#6200000
0#
#6210000
1#
b1011 ?
#6220000
0#
#6230000
1#
b1100 ?
#6240000
0#
#6250000
1#
b1101 ?
#6260000
0#
#6270000
1#
b1110 ?
#6280000
0#
#6290000
1#
b1111 ?
#6300000
0#
#6310000
1#
b10000 ?
#6320000
0#
#6330000
1#
b10001 ?
#6340000
0#
#6350000
1#
b10010 ?
#6360000
0#
#6370000
1#
b10011 ?
#6380000
0#
#6390000
1#
b10100 ?
#6400000
0#
#6410000
1#
b10101 ?
#6420000
0#
#6430000
1#
b10110 ?
#6440000
0#
#6450000
1#
b10111 ?
#6460000
0#
#6470000
1#
b11000 ?
#6480000
0#
#6490000
1#
b11001 ?
#6500000
0#
#6510000
1#
b11010 ?
#6520000
0#
#6530000
1#
b11011 ?
#6540000
0#
#6550000
1#
b11100 ?
#6560000
0#
#6570000
1#
b11101 ?
#6580000
0#
#6590000
1#
b11110 ?
#6600000
0#
#6610000
1#
b11111 ?
#6620000
0#
#6630000
1#
b100000 ?
#6640000
0#
#6650000
1#
b100001 ?
#6660000
0#
#6670000
1#
b100010 ?
#6680000
0#
#6690000
1#
b100011 ?
#6700000
0#
#6710000
1#
b100100 ?
#6720000
0#
#6730000
1#
b100101 ?
#6740000
0#
#6750000
1#
b100110 ?
#6760000
0#
#6770000
1#
b100111 ?
#6780000
0#
#6790000
1#
b101000 ?
#6800000
0#
#6810000
1#
b101001 ?
#6820000
0#
#6830000
1#
b101010 ?
#6840000
0#
#6850000
1#
b101011 ?
#6860000
0#
#6870000
1#
b101100 ?
#6880000
0#
#6890000
1#
b101101 ?
#6900000
0#
#6910000
1#
b101110 ?
#6920000
0#
#6930000
1#
b101111 ?
#6940000
0#
#6950000
1#
b10 &
b10 '
b110000 ?
#6960000
0#
#6970000
1#
b1 .
#6980000
0#
#6990000
1#
b10 .
#7000000
0#
#7010000
1#
b11 .
#7020000
0#
#7030000
1#
b100 .
#7040000
0#
#7050000
1#
b101 .
#7060000
0#
#7070000
1#
b110 .
#7080000
0#
#7090000
1#
b111 .
#7100000
0#
#7110000
1#
b1000 .
#7120000
0#
#7130000
1#
b1001 .
#7140000
0#
#7150000
1#
b1010 .
#7160000
0#
#7170000
1#
b1011 .
#7180000
0#
#7190000
1#
b1100 .
#7200000
0#
#7210000
1#
b1101 .
#7220000
0#
#7230000
1#
b1110 .
#7240000
0#
#7250000
1#
b1111 .
#7260000
0#
#7270000
1#
b11 &
b11 '
b10000 .
#7280000
0#
#7290000
1#
b1 /
#7300000
0#
#7310000
1#
b10 /
#7320000
0#
#7330000
1#
b11 /
#7340000
0#
#7350000
1#
b100 /
#7360000
0#
#7370000
1#
b101 /
#7380000
0#
#7390000
1#
b110 /
#7400000
0#
#7410000
1#
b111 /
#7420000
0#
#7430000
1#
b1000 /
#7440000
0#
#7450000
1#
b1001 /
#7460000
0#
#7470000
1#
b1010 /
#7480000
0#
#7490000
1#
b1011 /
#7500000
0#
#7510000
1#
b1100 /
#7520000
0#
#7530000
1#
b1101 /
#7540000
0#
#7550000
1#
b1110 /
#7560000
0#
#7570000
1#
b1111 /
#7580000
0#
#7590000
1#
0$
b10000 /
#7600000
0#
#7610000
1#
1$
#7620000
0#
#7630000
b1 *
b1 )
1#
b1 &
b1 '
#7640000
0#
#7650000
b10 *
1#
b1 0
#7660000
0#
#7670000
b11 *
1#
b10 0
#7680000
0#
#7690000
b100 *
1#
b11 0
#7700000
0#
#7710000
b101 *
1#
b100 0
#7720000
0#
#7730000
b110 *
1#
b101 0
#7740000
0#
#7750000
b111 *
1#
b110 0
#7760000
0#
#7770000
b1000 *
1#
b111 0
#7780000
0#
#7790000
b1001 *
1#
b1000 0
#7800000
0#
#7810000
b1010 *
1#
b1001 0
#7820000
0#
#7830000
b1011 *
1#
b1010 0
#7840000
0#
#7850000
b1100 *
1#
b1011 0
#7860000
0#
#7870000
b1101 *
1#
b1100 0
#7880000
0#
#7890000
b1110 *
1#
b1101 0
#7900000
0#
#7910000
b1111 *
1#
b1110 0
#7920000
0#
#7930000
b10000 *
1#
b1111 0
#7940000
0#
#7950000
b10001 *
1#
b10000 0
#7960000
0#
#7970000
b10010 *
1#
b10001 0
#7980000
0#
#7990000
b10011 *
1#
b10010 0
#8000000
0#
#8010000
b10100 *
1#
b10011 0
#8020000
0#
#8030000
b10101 *
1#
b10100 0
#8040000
0#
#8050000
b10110 *
1#
b10101 0
#8060000
0#
#8070000
b10111 *
1#
b10110 0
#8080000
0#
#8090000
b11000 *
1#
b10111 0
#8100000
0#
#8110000
b11001 *
1#
b11000 0
#8120000
0#
#8130000
b11010 *
1#
b11001 0
#8140000
0#
#8150000
b11011 *
1#
b11010 0
#8160000
0#
#8170000
b11100 *
1#
b11011 0
#8180000
0#
#8190000
b11101 *
1#
b11100 0
#8200000
0#
#8210000
b11110 *
1#
b11101 0
#8220000
0#
#8230000
b11111 *
1#
b11110 0
#8240000
0#
#8250000
b100000 *
1#
b11111 0
#8260000
0#
#8270000
b100001 *
1#
b100000 0
#8280000
0#
#8290000
b100010 *
1#
b100001 0
#8300000
0#
#8310000
b100011 *
1#
b100010 0
#8320000
0#
#8330000
b100100 *
1#
b100011 0
#8340000
0#
#8350000
b100101 *
1#
b100100 0
#8360000
0#
#8370000
b100110 *
1#
b100101 0
#8380000
0#
#8390000
b100111 *
1#
b100110 0
#8400000
0#
#8410000
b101000 *
1#
b100111 0
#8420000
0#
#8430000
b101001 *
1#
b101000 0
#8440000
0#
#8450000
b101010 *
1#
b101001 0
#8460000
0#
#8470000
b101011 *
1#
b101010 0
#8480000
0#
#8490000
b101100 *
1#
b101011 0
#8500000
0#
#8510000
b101101 *
1#
b101100 0
#8520000
0#
#8530000
b101110 *
1#
b101101 0
#8540000
0#
#8550000
b101111 *
1#
b101110 0
#8560000
0#
#8570000
b110000 *
1#
b101111 0
#8580000
0#
#8590000
b110001 *
1#
b110000 0
#8600000
0#
#8610000
b110010 *
1#
b110001 0
#8620000
0#
#8630000
b110011 *
1#
b110010 0
#8640000
0#
#8650000
b110100 *
1#
b110011 0
#8660000
0#
#8670000
b110101 *
1#
b110100 0
#8680000
0#
#8690000
b110110 *
1#
b110101 0
#8700000
0#
#8710000
b110111 *
1#
b110110 0
#8720000
0#
#8730000
b10 )
b0 *
1#
b110111 0
#8740000
0#
#8750000
b1 +
1#
b111000 0
#8760000
0#
#8770000
b10 +
1#
b1 1
#8780000
0#
#8790000
b11 +
1#
b10 1
#8800000
0#
