src/ether.sv
`default_nettype none
`timescale 1ns / 1ps

module ether(
	input wire clk,
	input wire rst,
	input wire [1:0] rxd,
	input wire crsdv,

	output logic axiov,
	output logic [1:0] axiod
);


logic[3:0] now_state;
logic [5:0] rxd_count;
logic [2:0] sfd_count;
/*
* 0000: ready state
* 0001: validating preamble
* 0010: validating SFD
* 0100: reading data
*/
always_ff @(posedge clk)begin
	if(rst)begin
		rxd_count <= 0;
		sfd_count <= 0;
		axiov <= 0;
		axiod <= 2'b00; //reset?
		now_state <= 4'b0000;
	end
	else begin
		if(crsdv)begin
			case(now_state)
				4'b0000:begin
					if(rxd == 2'b01)begin
						//shift to preamble validation
						now_state <= 4'b0001;
						rxd_count <= 1;
					end
				end
				4'b0001:begin
					if(rxd == 2'b01)begin
						if(rxd_count == 6'd55)begin
							//preamble validating done
							rxd_count <= 0;
							now_state <= 4'b0010;
						end else begin
							//still validating
							rxd_count <= rxd_count + 1;
						end
					end else begin
						//invalid, back to ready state
						rxd_count <= 0;
						now_state <= 4'b0000;
					end
				end
				4'b0010:begin
					//validate sfd
					if(sfd_count < 3)begin
						if(rxd == 2'b01)begin
							//still validating
							sfd_count <= sfd_count + 1;
						end else begin
							//invalid, back to ready state
							sfd_count <= 0;
							now_state <= 4'b0000;
						end
					end else if(sfd_count == 3)begin
						if(rxd == 2'b11)begin
							//sfd check done, start reading
							sfd_count <= 0;
							now_state <= 4'b0100;
						end else begin
							//invalid, back to ready state
							sfd_count <= 0;
							now_state <= 4'b0000;
						end
					end
				end
				4'b0100:begin
					if(crsdv)begin
						//not finished reading, read more
						axiov <= 1;
						axiod <= rxd;
					end else begin
						//end of packet, back to ready state
						axiov <= 0;
						axiod <= 2'b00;
						now_state <= 4'b0000;
					end
				end
			endcase
		end else begin
			//same as reset
			rxd_count <= 0;
                	sfd_count <= 0;
                	axiov <= 0;
                	axiod <= 2'b00; //reset?
                	now_state <= 4'b0000;
		end
	end


end
endmodule
`default_nettype wire

sim/ether_tb.sv
`default_nettype none
`timescale 1ns / 1ps

module ether_tb;

logic clk;
logic rst;

logic [1:0] rxd;
logic crsdv;

logic [1:0] axiod;
logic axiov;

logic [47:0] addr_d,addr_s;
logic [15:0] length;
logic [15:0] data;
logic [31:0] fcs;
ether uut(
	.clk(clk),
	.rst(rst),
	.rxd(rxd),
	.crsdv(crsdv),
	.axiov(axiov),
	.axiod(axiod));

always begin
	#10;
       	clk = !clk;
end

initial begin
	$dumpfile("ether.vcd");
	$dumpvars(0,ether_tb);
	$display("Starting Sim");
	clk = 0;
	#20;
	rst = 1;
	#10;
	rst = 0;
	#10;
	crsdv = 1;
	//test case 1: valid packet
	//valid preamble
	for(int i = 0;i<56;i=i+1)begin
		rxd = 2'b01;
		#20;
	end
	//valid sfd
	for(int i = 0;i<4;i = i+1)begin
		if(i < 3)begin
			rxd = 2'b01;
		end else begin
			rxd = 2'b11;
		end
		#20;
	end
	//D.A.
	for(int i = 0;i < 48;i=i+1)begin
		rxd = 2'b11;
		#20;
	end
	//S.A.
	for(int i = 0;i <48;i=i+1)begin
		rxd = 2'b11;
		#20;
	end
	//Data
	for(int i = 0;i < 16;i = i+1)begin
		rxd = 2'b10;
		#20;
	end
	//FCS
	for(int i = 0;i < 16;i = i+1)begin
		rxd = 2'b11;
		#20;
	end
	crsdv = 0;
	#20;
	crsdv = 1;
	#20;
	//test case 2: invalid preamble
	//invalid preamble
        for(int i = 0;i<56;i=i+1)begin
		if(i == 20)begin
			rxd = 2'b10;
		end else begin
			rxd = 2'b01;
		end
                #20;
        end
        //valid sfd
        for(int i = 0;i<4;i = i+1)begin
                if(i < 3)begin
                        rxd = 2'b01;
                end else begin
                        rxd = 2'b11;
                end
                #20;
        end
        //D.A.
        for(int i = 0;i < 48;i=i+1)begin
                rxd = 2'b11;
                #20;
        end
        //S.A.
        for(int i = 0;i <48;i=i+1)begin
                rxd = 2'b11;
                #20;
        end
        //Data
        for(int i = 0;i < 16;i = i+1)begin
                rxd = 2'b10;
                #20;
        end
        //FCS
        for(int i = 0;i < 16;i = i+1)begin
                rxd = 2'b11;
                #20;
        end
        crsdv = 0;
        #20;
	crsdv = 1;
	#20;
	//test case 3: invalid preamble
	//invalid preamble
        for(int i = 0;i<56;i=i+1)begin
		rxd = 2'b01;
                #20;
        end
        //valid sfd
        for(int i = 0;i<4;i = i+1)begin
		if(i == 1)begin
			rxd = 2'b11;
		end else if(i ==3)begin
			rxd = 2'b11;
		end else begin
			rxd = 2'b01;
		end
                #20;
        end
        //D.A.
        for(int i = 0;i < 48;i=i+1)begin
                rxd = 2'b11;
                #20;
        end
        //S.A.
        for(int i = 0;i <48;i=i+1)begin
                rxd = 2'b11;
                #20;
        end
        //Data
        for(int i = 0;i < 16;i = i+1)begin
                rxd = 2'b10;
                #20;
        end
        //FCS
        for(int i = 0;i < 16;i = i+1)begin
                rxd = 2'b11;
                #20;
        end
        crsdv = 0;
        #20;


	$display("Finishing Sim");
	$finish;
end
endmodule

`default_nettype wire

ether.vcd
$date
	Mon Oct 24 21:57:50 2022
$end
$version
	Icarus Verilog
$end
$timescale
	1ps
$end
$scope module ether_tb $end
$var wire 1 ! axiov $end
$var wire 2 " axiod [1:0] $end
$var reg 1 # clk $end
$var reg 1 $ crsdv $end
$var reg 1 % rst $end
$var reg 2 & rxd [1:0] $end
$scope module uut $end
$var wire 1 # clk $end
$var wire 1 $ crsdv $end
$var wire 1 % rst $end
$var wire 2 ' rxd [1:0] $end
$var reg 2 ( axiod [1:0] $end
$var reg 1 ! axiov $end
$var reg 4 ) now_state [3:0] $end
$var reg 6 * rxd_count [5:0] $end
$var reg 3 + sfd_count [2:0] $end
$upscope $end
$scope begin $ivl_for_loop0 $end
$var integer 32 , i [31:0] $end
$upscope $end
$scope begin $ivl_for_loop1 $end
$var integer 32 - i [31:0] $end
$upscope $end
$scope begin $ivl_for_loop10 $end
$var integer 32 . i [31:0] $end
$upscope $end
$scope begin $ivl_for_loop11 $end
$var integer 32 / i [31:0] $end
$upscope $end
$scope begin $ivl_for_loop12 $end
$var integer 32 0 i [31:0] $end
$upscope $end
$scope begin $ivl_for_loop13 $end
$var integer 32 1 i [31:0] $end
$upscope $end
$scope begin $ivl_for_loop14 $end
$var integer 32 2 i [31:0] $end
$upscope $end
$scope begin $ivl_for_loop15 $end
$var integer 32 3 i [31:0] $end
$upscope $end
$scope begin $ivl_for_loop16 $end
$var integer 32 4 i [31:0] $end
$upscope $end
$scope begin $ivl_for_loop17 $end
$var integer 32 5 i [31:0] $end
$upscope $end
$scope begin $ivl_for_loop2 $end
$var integer 32 6 i [31:0] $end
$upscope $end
$scope begin $ivl_for_loop3 $end
$var integer 32 7 i [31:0] $end
$upscope $end
$scope begin $ivl_for_loop4 $end
$var integer 32 8 i [31:0] $end
$upscope $end
$scope begin $ivl_for_loop5 $end
$var integer 32 9 i [31:0] $end
$upscope $end
$scope begin $ivl_for_loop6 $end
$var integer 32 : i [31:0] $end
$upscope $end
$scope begin $ivl_for_loop7 $end
$var integer 32 ; i [31:0] $end
$upscope $end
$scope begin $ivl_for_loop8 $end
$var integer 32 < i [31:0] $end
$upscope $end
$scope begin $ivl_for_loop9 $end
$var integer 32 = i [31:0] $end
$upscope $end
$upscope $end
$enddefinitions $end
#0
$dumpvars
b0 =
b0 <
b0 ;
b0 :
b0 9
b0 8
b0 7
b0 6
b0 5
b0 4
b0 3
b0 2
b0 1
b0 0
b0 /
b0 .
b0 -
b0 ,
bx +
bx *
bx )
bx (
bx '
bx &
x%
x$
0#
bx "
x!
$end
#10000
b0 )
b0 "
b0 (
0!
b0 +
b0 *
1#
#20000
0#
1%
#30000
1#
0%
#40000
0#
b1 &
b1 '
1$
#50000
b1 *
b1 )
1#
#60000
0#
b1 ,
#70000
b10 *
1#
#80000
0#
b10 ,
#90000
b11 *
1#
#100000
0#
b11 ,
#110000
b100 *
1#
#120000
0#
b100 ,
#130000
b101 *
1#
#140000
0#
b101 ,
#150000
b110 *
1#
#160000
0#
b110 ,
#170000
b111 *
1#
#180000
0#
b111 ,
#190000
b1000 *
1#
#200000
0#
b1000 ,
#210000
b1001 *
1#
#220000
0#
b1001 ,
#230000
b1010 *
1#
#240000
0#
b1010 ,
#250000
b1011 *
1#
#260000
0#
b1011 ,
#270000
b1100 *
1#
#280000
0#
b1100 ,
#290000
b1101 *
1#
#300000
0#
b1101 ,
#310000
b1110 *
1#
#320000
0#
b1110 ,
#330000
b1111 *
1#
#340000
0#
b1111 ,
#350000
b10000 *
1#
#360000
0#
b10000 ,
#370000
b10001 *
1#
#380000
0#
b10001 ,
#390000
b10010 *
1#
#400000
0#
b10010 ,
#410000
b10011 *
1#
#420000
0#
b10011 ,
#430000
b10100 *
1#
#440000
0#
b10100 ,
#450000
b10101 *
1#
#460000
0#
b10101 ,
#470000
b10110 *
1#
#480000
0#
b10110 ,
#490000
b10111 *
1#
#500000
0#
b10111 ,
#510000
b11000 *
1#
#520000
0#
b11000 ,
#530000
b11001 *
1#
#540000
0#
b11001 ,
#550000
b11010 *
1#
#560000
0#
b11010 ,
#570000
b11011 *
1#
#580000
0#
b11011 ,
#590000
b11100 *
1#
#600000
0#
b11100 ,
#610000
b11101 *
1#
#620000
0#
b11101 ,
#630000
b11110 *
1#
#640000
0#
b11110 ,
#650000
b11111 *
1#
#660000
0#
b11111 ,
#670000
b100000 *
1#
#680000
0#
b100000 ,
#690000
b100001 *
1#
#700000
0#
b100001 ,
#710000
b100010 *
1#
#720000
0#
b100010 ,
#730000
b100011 *
1#
#740000
0#
b100011 ,
#750000
b100100 *
1#
#760000
0#
b100100 ,
#770000
b100101 *
1#
#780000
0#
b100101 ,
#790000
b100110 *
1#
#800000
0#
b100110 ,
#810000
b100111 *
1#
#820000
0#
b100111 ,
#830000
b101000 *
1#
#840000
0#
b101000 ,
#850000
b101001 *
1#
#860000
0#
b101001 ,
#870000
b101010 *
1#
#880000
0#
b101010 ,
#890000
b101011 *
1#
#900000
0#
b101011 ,
#910000
b101100 *
1#
#920000
0#
b101100 ,
#930000
b101101 *
1#
#940000
0#
b101101 ,
#950000
b101110 *
1#
#960000
0#
b101110 ,
#970000
b101111 *
1#
#980000
0#
b101111 ,
#990000
b110000 *
1#
#1000000
0#
b110000 ,
#1010000
b110001 *
1#
#1020000
0#
b110001 ,
#1030000
b110010 *
1#
#1040000
0#
b110010 ,
#1050000
b110011 *
1#
#1060000
0#
b110011 ,
#1070000
b110100 *
1#
#1080000
0#
b110100 ,
#1090000
b110101 *
1#
#1100000
0#
b110101 ,
#1110000
b110110 *
1#
#1120000
0#
b110110 ,
#1130000
b110111 *
1#
#1140000
0#
b110111 ,
#1150000
b10 )
b0 *
1#
#1160000
0#
b111000 ,
#1170000
b1 +
1#
#1180000
0#
b1 -
#1190000
b10 +
1#
#1200000
0#
b10 -
#1210000
b11 +
1#
#1220000
0#
b11 &
b11 '
b11 -
#1230000
b100 )
b0 +
1#
#1240000
0#
b100 -
#1250000
b11 "
b11 (
1!
1#
#1260000
0#
b1 6
#1270000
1#
#1280000
0#
b10 6
#1290000
1#
#1300000
0#
b11 6
#1310000
1#
#1320000
0#
b100 6
#1330000
1#
#1340000
0#
b101 6
#1350000
1#
#1360000
0#
b110 6
#1370000
1#
#1380000
0#
b111 6
#1390000
1#
#1400000
0#
b1000 6
#1410000
1#
#1420000
0#
b1001 6
#1430000
1#
#1440000
0#
b1010 6
#1450000
1#
#1460000
0#
b1011 6
#1470000
1#
#1480000
0#
b1100 6
#1490000
1#
#1500000
0#
b1101 6
#1510000
1#
#1520000
0#
b1110 6
#1530000
1#
#1540000
0#
b1111 6
#1550000
1#
#1560000
0#
b10000 6
#1570000
1#
#1580000
0#
b10001 6
#1590000
1#
#1600000
0#
b10010 6
#1610000
1#
#1620000
0#
b10011 6
#1630000
1#
#1640000
0#
b10100 6
#1650000
1#
#1660000
0#
b10101 6
#1670000
1#
#1680000
0#
b10110 6
#1690000
1#
#1700000
0#
b10111 6
#1710000
1#
#1720000
0#
b11000 6
#1730000
1#
#1740000
0#
b11001 6
#1750000
1#
#1760000
0#
b11010 6
#1770000
1#
#1780000
0#
b11011 6
#1790000
1#
#1800000
0#
b11100 6
#1810000
1#
#1820000
0#
b11101 6
#1830000
1#
#1840000
0#
b11110 6
#1850000
1#
#1860000
0#
b11111 6
#1870000
1#
#1880000
0#
b100000 6
#1890000
1#
#1900000
0#
b100001 6
#1910000
1#
#1920000
0#
b100010 6
#1930000
1#
#1940000
0#
b100011 6
#1950000
1#
#1960000
0#
b100100 6
#1970000
1#
#1980000
0#
b100101 6
#1990000
1#
#2000000
0#
b100110 6
#2010000
1#
#2020000
0#
b100111 6
#2030000
1#
#2040000
0#
b101000 6
#2050000
1#
#2060000
0#
b101001 6
#2070000
1#
#2080000
0#
b101010 6
#2090000
1#
#2100000
0#
b101011 6
#2110000
1#
#2120000
0#
b101100 6
#2130000
1#
#2140000
0#
b101101 6
#2150000
1#
#2160000
0#
b101110 6
#2170000
1#
#2180000
0#
b101111 6
#2190000
1#
#2200000
0#
b110000 6
#2210000
1#
#2220000
0#
b1 7
#2230000
1#
#2240000
0#
b10 7
#2250000
1#
#2260000
0#
b11 7
#2270000
1#
#2280000
0#
b100 7
#2290000
1#
#2300000
0#
b101 7
#2310000
1#
#2320000
0#
b110 7
#2330000
1#
#2340000
0#
b111 7
#2350000
1#
#2360000
0#
b1000 7
#2370000
1#
#2380000
0#
b1001 7
#2390000
1#
#2400000
0#
b1010 7
#2410000
1#
#2420000
0#
b1011 7
#2430000
1#
#2440000
0#
b1100 7
#2450000
1#
#2460000
0#
b1101 7
#2470000
1#
#2480000
0#
b1110 7
#2490000
1#
#2500000
0#
b1111 7
#2510000
1#
#2520000
0#
b10000 7
#2530000
1#
#2540000
0#
b10001 7
#2550000
1#
#2560000
0#
b10010 7
#2570000
1#
#2580000
0#
b10011 7
#2590000
1#
#2600000
0#
b10100 7
#2610000
1#
#2620000
0#
b10101 7
#2630000
1#
#2640000
0#
b10110 7
#2650000
1#
#2660000
0#
b10111 7
#2670000
1#
#2680000
0#
b11000 7
#2690000
1#
#2700000
0#
b11001 7
#2710000
1#
#2720000
0#
b11010 7
#2730000
1#
#2740000
0#
b11011 7
#2750000
1#
#2760000
0#
b11100 7
#2770000
1#
#2780000
0#
b11101 7
#2790000
1#
#2800000
0#
b11110 7
#2810000
1#
#2820000
0#
b11111 7
#2830000
1#
#2840000
0#
b100000 7
#2850000
1#
#2860000
0#
b100001 7
#2870000
1#
#2880000
0#
b100010 7
#2890000
1#
#2900000
0#
b100011 7
#2910000
1#
#2920000
0#
b100100 7
#2930000
1#
#2940000
0#
b100101 7
#2950000
1#
#2960000
0#
b100110 7
#2970000
1#
#2980000
0#
b100111 7
#2990000
1#
#3000000
0#
b101000 7
#3010000
1#
#3020000
0#
b101001 7
#3030000
1#
#3040000
0#
b101010 7
#3050000
1#
#3060000
0#
b101011 7
#3070000
1#
#3080000
0#
b101100 7
#3090000
1#
#3100000
0#
b101101 7
#3110000
1#
#3120000
0#
b101110 7
#3130000
1#
#3140000
0#
b101111 7
#3150000
1#
#3160000
0#
b10 &
b10 '
b110000 7
#3170000
b10 "
b10 (
1#
#3180000
0#
b1 8
#3190000
1#
#3200000
0#
b10 8
#3210000
1#
#3220000
0#
b11 8
#3230000
1#
#3240000
0#
b100 8
#3250000
1#
#3260000
0#
b101 8
#3270000
1#
#3280000
0#
b110 8
#3290000
1#
#3300000
0#
b111 8
#3310000
1#
#3320000
0#
b1000 8
#3330000
1#
#3340000
0#
b1001 8
#3350000
1#
#3360000
0#
b1010 8
#3370000
1#
#3380000
0#
b1011 8
#3390000
1#
#3400000
0#
b1100 8
#3410000
1#
#3420000
0#
b1101 8
#3430000
1#
#3440000
0#
b1110 8
#3450000
1#
#3460000
0#
b1111 8
#3470000
1#
#3480000
0#
b11 &
b11 '
b10000 8
#3490000
b11 "
b11 (
1#
#3500000
0#
b1 9
#3510000
1#
#3520000
0#
b10 9
#3530000
1#
#3540000
0#
b11 9
#3550000
1#
#3560000
0#
b100 9
#3570000
1#
#3580000
0#
b101 9
#3590000
1#
#3600000
0#
b110 9
#3610000
1#
#3620000
0#
b111 9
#3630000
1#
#3640000
0#
b1000 9
#3650000
1#
#3660000
0#
b1001 9
#3670000
1#
#3680000
0#
b1010 9
#3690000
1#
#3700000
0#
b1011 9
#3710000
1#
#3720000
0#
b1100 9
#3730000
1#
#3740000
0#
b1101 9
#3750000
1#
#3760000
0#
b1110 9
#3770000
1#
#3780000
0#
b1111 9
#3790000
1#
#3800000
0#
0$
b10000 9
#3810000
b0 )
b0 "
b0 (
0!
1#
#3820000
0#
1$
#3830000
1#
#3840000
0#
b1 &
b1 '
#3850000
b1 *
b1 )
1#
#3860000
0#
b1 :
#3870000
b10 *
1#
#3880000
0#
b10 :
#3890000
b11 *
1#
#3900000
0#
b11 :
#3910000
b100 *
1#
#3920000
0#
b100 :
#3930000
b101 *
1#
#3940000
0#
b101 :
#3950000
b110 *
1#
#3960000
0#
b110 :
#3970000
b111 *
1#
#3980000
0#
b111 :
#3990000
b1000 *
1#
#4000000
0#
b1000 :
#4010000
b1001 *
1#
#4020000
0#
b1001 :
#4030000
b1010 *
1#
#4040000
0#
b1010 :
#4050000
b1011 *
1#
#4060000
0#
b1011 :
#4070000
b1100 *
1#
#4080000
0#
b1100 :
#4090000
b1101 *
1#
#4100000
0#
b1101 :
#4110000
b1110 *
1#
#4120000
0#
b1110 :
#4130000
b1111 *
1#
#4140000
0#
b1111 :
#4150000
b10000 *
1#
#4160000
0#
b10000 :
#4170000
b10001 *
1#
#4180000
0#
b10001 :
#4190000
b10010 *
1#
#4200000
0#
b10010 :
#4210000
b10011 *
1#
#4220000
0#
b10011 :
#4230000
b10100 *
1#
#4240000
0#
b10 &
b10 '
b10100 :
#4250000
b0 )
b0 *
1#
#4260000
0#
b1 &
b1 '
b10101 :
#4270000
b1 *
b1 )
1#
#4280000
0#
b10110 :
#4290000
b10 *
1#
#4300000
0#
b10111 :
#4310000
b11 *
1#
#4320000
0#
b11000 :
#4330000
b100 *
1#
#4340000
0#
b11001 :
#4350000
b101 *
1#
#4360000
0#
b11010 :
#4370000
b110 *
1#
#4380000
0#
b11011 :
#4390000
b111 *
1#
#4400000
0#
b11100 :
#4410000
b1000 *
1#
#4420000
0#
b11101 :
#4430000
b1001 *
1#
#4440000
0#
b11110 :
#4450000
b1010 *
1#
#4460000
0#
b11111 :
#4470000
b1011 *
1#
#4480000
0#
b100000 :
#4490000
b1100 *
1#
#4500000
0#
b100001 :
#4510000
b1101 *
1#
#4520000
0#
b100010 :
#4530000
b1110 *
1#
#4540000
0#
b100011 :
#4550000
b1111 *
1#
#4560000
0#
b100100 :
#4570000
b10000 *
1#
#4580000
0#
b100101 :
#4590000
b10001 *
1#
#4600000
0#
b100110 :
#4610000
b10010 *
1#
#4620000
0#
b100111 :
#4630000
b10011 *
1#
#4640000
0#
b101000 :
#4650000
b10100 *
1#
#4660000
0#
b101001 :
#4670000
b10101 *
1#
#4680000
0#
b101010 :
#4690000
b10110 *
1#
#4700000
0#
b101011 :
#4710000
b10111 *
1#
#4720000
0#
b101100 :
#4730000
b11000 *
1#
#4740000
0#
b101101 :
#4750000
b11001 *
1#
#4760000
0#
b101110 :
#4770000
b11010 *
1#
#4780000
0#
b101111 :
#4790000
b11011 *
1#
#4800000
0#
b110000 :
#4810000
b11100 *
1#
#4820000
0#
b110001 :
#4830000
b11101 *
1#
#4840000
0#
b110010 :
#4850000
b11110 *
1#
#4860000
0#
b110011 :
#4870000
b11111 *
1#
#4880000
0#
b110100 :
#4890000
b100000 *
1#
#4900000
0#
b110101 :
#4910000
b100001 *
1#
#4920000
0#
b110110 :
#4930000
b100010 *
1#
#4940000
0#
b110111 :
#4950000
b100011 *
1#
#4960000
0#
b111000 :
#4970000
b100100 *
1#
#4980000
0#
b1 ;
#4990000
b100101 *
1#
#5000000
0#
b10 ;
#5010000
b100110 *
1#
#5020000
0#
b11 &
b11 '
b11 ;
#5030000
b0 )
b0 *
1#
#5040000
0#
b100 ;
#5050000
1#
#5060000
0#
b1 <
#5070000
1#
#5080000
0#
b10 <
#5090000
1#
#5100000
0#
b11 <
#5110000
1#
#5120000
0#
b100 <
#5130000
1#
#5140000
0#
b101 <
#5150000
1#
#5160000
0#
b110 <
#5170000
1#
#5180000
0#
b111 <
#5190000
1#
#5200000
0#
b1000 <
#5210000
1#
#5220000
0#
b1001 <
#5230000
1#
#5240000
0#
b1010 <
#5250000
1#
#5260000
0#
b1011 <
#5270000
1#
#5280000
0#
b1100 <
#5290000
1#
#5300000
0#
b1101 <
#5310000
1#
#5320000
0#
b1110 <
#5330000
1#
#5340000
0#
b1111 <
#5350000
1#
#5360000
0#
b10000 <
#5370000
1#
#5380000
0#
b10001 <
#5390000
1#
#5400000
0#
b10010 <
#5410000
1#
#5420000
0#
b10011 <
#5430000
1#
#5440000
0#
b10100 <
#5450000
1#
#5460000
0#
b10101 <
#5470000
1#
#5480000
0#
b10110 <
#5490000
1#
#5500000
0#
b10111 <
#5510000
1#
#5520000
0#
b11000 <
#5530000
1#
#5540000
0#
b11001 <
#5550000
1#
#5560000
0#
b11010 <
#5570000
1#
#5580000
0#
b11011 <
#5590000
1#
#5600000
0#
b11100 <
#5610000
1#
#5620000
0#
b11101 <
#5630000
1#
#5640000
0#
b11110 <
#5650000
1#
#5660000
0#
b11111 <
#5670000
1#
#5680000
0#
b100000 <
#5690000
1#
#5700000
0#
b100001 <
#5710000
1#
#5720000
0#
b100010 <
#5730000
1#
#5740000
0#
b100011 <
#5750000
1#
#5760000
0#
b100100 <
#5770000
1#
#5780000
0#
b100101 <
#5790000
1#
#5800000
0#
b100110 <
#5810000
1#
#5820000
0#
b100111 <
#5830000
1#
#5840000
0#
b101000 <
#5850000
1#
#5860000
0#
b101001 <
#5870000
1#
#5880000
0#
b101010 <
#5890000
1#
#5900000
0#
b101011 <
#5910000
1#
#5920000
0#
b101100 <
#5930000
1#
#5940000
0#
b101101 <
#5950000
1#
#5960000
0#
b101110 <
#5970000
1#
#5980000
0#
b101111 <
#5990000
1#
#6000000
0#
b110000 <
#6010000
1#
#6020000
0#
b1 =
#6030000
1#
#6040000
0#
b10 =
#6050000
1#
#6060000
0#
b11 =
#6070000
1#
#6080000
0#
b100 =
#6090000
1#
#6100000
0#
b101 =
#6110000
1#
#6120000
0#
b110 =
#6130000
1#
#6140000
0#
b111 =
#6150000
1#
#6160000
0#
b1000 =
#6170000
1#
#6180000
0#
b1001 =
#6190000
1#
#6200000
0#
b1010 =
#6210000
1#
#6220000
0#
b1011 =
#6230000
1#
#6240000
0#
b1100 =
#6250000
1#
#6260000
0#
b1101 =
#6270000
1#
#6280000
0#
b1110 =
#6290000
1#
#6300000
0#
b1111 =
#6310000
1#
#6320000
0#
b10000 =
#6330000
1#
#6340000
0#
b10001 =
#6350000
1#
#6360000
0#
b10010 =
#6370000
1#
#6380000
0#
b10011 =
#6390000
1#
#6400000
0#
b10100 =
#6410000
1#
#6420000
0#
b10101 =
#6430000
1#
#6440000
0#
b10110 =
#6450000
1#
#6460000
0#
b10111 =
#6470000
1#
#6480000
0#
b11000 =
#6490000
1#
#6500000
0#
b11001 =
#6510000
1#
#6520000
0#
b11010 =
#6530000
1#
#6540000
0#
b11011 =
#6550000
1#
#6560000
0#
b11100 =
#6570000
1#
#6580000
0#
b11101 =
#6590000
1#
#6600000
0#
b11110 =
#6610000
1#
#6620000
0#
b11111 =
#6630000
1#
#6640000
0#
b100000 =
#6650000
1#
#6660000
0#
b100001 =
#6670000
1#
#6680000
0#
b100010 =
#6690000
1#
#6700000
0#
b100011 =
#6710000
1#
#6720000
0#
b100100 =
#6730000
1#
#6740000
0#
b100101 =
#6750000
1#
#6760000
0#
b100110 =
#6770000
1#
#6780000
0#
b100111 =
#6790000
1#
#6800000
0#
b101000 =
#6810000
1#
#6820000
0#
b101001 =
#6830000
1#
#6840000
0#
b101010 =
#6850000
1#
#6860000
0#
b101011 =
#6870000
1#
#6880000
0#
b101100 =
#6890000
1#
#6900000
0#
b101101 =
#6910000
1#
#6920000
0#
b101110 =
#6930000
1#
#6940000
0#
b101111 =
#6950000
1#
#6960000
0#
b10 &
b10 '
b110000 =
#6970000
1#
#6980000
0#
b1 .
#6990000
1#
#7000000
0#
b10 .
#7010000
1#
#7020000
0#
b11 .
#7030000
1#
#7040000
0#
b100 .
#7050000
1#
#7060000
0#
b101 .
#7070000
1#
#7080000
0#
b110 .
#7090000
1#
#7100000
0#
b111 .
#7110000
1#
#7120000
0#
b1000 .
#7130000
1#
#7140000
0#
b1001 .
#7150000
1#
#7160000
0#
b1010 .
#7170000
1#
#7180000
0#
b1011 .
#7190000
1#
#7200000
0#
b1100 .
#7210000
1#
#7220000
0#
b1101 .
#7230000
1#
#7240000
0#
b1110 .
#7250000
1#
#7260000
0#
b1111 .
#7270000
1#
#7280000
0#
b11 &
b11 '
b10000 .
#7290000
1#
#7300000
0#
b1 /
#7310000
1#
#7320000
0#
b10 /
#7330000
1#
#7340000
0#
b11 /
#7350000
1#
#7360000
0#
b100 /
#7370000
1#
#7380000
0#
b101 /
#7390000
1#
#7400000
0#
b110 /
#7410000
1#
#7420000
0#
b111 /
#7430000
1#
#7440000
0#
b1000 /
#7450000
1#
#7460000
0#
b1001 /
#7470000
1#
#7480000
0#
b1010 /
#7490000
1#
#7500000
0#
b1011 /
#7510000
1#
#7520000
0#
b1100 /
#7530000
1#
#7540000
0#
b1101 /
#7550000
1#
#7560000
0#
b1110 /
#7570000
1#
#7580000
0#
b1111 /
#7590000
1#
#7600000
0#
0$
b10000 /
#7610000
1#
#7620000
0#
1$
#7630000
1#
#7640000
0#
b1 &
b1 '
#7650000
b1 *
b1 )
1#
#7660000
0#
b1 0
#7670000
b10 *
1#
#7680000
0#
b10 0
#7690000
b11 *
1#
#7700000
0#
b11 0
#7710000
b100 *
1#
#7720000
0#
b100 0
#7730000
b101 *
1#
#7740000
0#
b101 0
#7750000
b110 *
1#
#7760000
0#
b110 0
#7770000
b111 *
1#
#7780000
0#
b111 0
#7790000
b1000 *
1#
#7800000
0#
b1000 0
#7810000
b1001 *
1#
#7820000
0#
b1001 0
#7830000
b1010 *
1#
#7840000
0#
b1010 0
#7850000
b1011 *
1#
#7860000
0#
b1011 0
#7870000
b1100 *
1#
#7880000
0#
b1100 0
#7890000
b1101 *
1#
#7900000
0#
b1101 0
#7910000
b1110 *
1#
#7920000
0#
b1110 0
#7930000
b1111 *
1#
#7940000
0#
b1111 0
#7950000
b10000 *
1#
#7960000
0#
b10000 0
#7970000
b10001 *
1#
#7980000
0#
b10001 0
#7990000
b10010 *
1#
#8000000
0#
b10010 0
#8010000
b10011 *
1#
#8020000
0#
b10011 0
#8030000
b10100 *
1#
#8040000
0#
b10100 0
#8050000
b10101 *
1#
#8060000
0#
b10101 0
#8070000
b10110 *
1#
#8080000
0#
b10110 0
#8090000
b10111 *
1#
#8100000
0#
b10111 0
#8110000
b11000 *
1#
#8120000
0#
b11000 0
#8130000
b11001 *
1#
#8140000
0#
b11001 0
#8150000
b11010 *
1#
#8160000
0#
b11010 0
#8170000
b11011 *
1#
#8180000
0#
b11011 0
#8190000
b11100 *
1#
#8200000
0#
b11100 0
#8210000
b11101 *
1#
#8220000
0#
b11101 0
#8230000
b11110 *
1#
#8240000
0#
b11110 0
#8250000
b11111 *
1#
#8260000
0#
b11111 0
#8270000
b100000 *
1#
#8280000
0#
b100000 0
#8290000
b100001 *
1#
#8300000
0#
b100001 0
#8310000
b100010 *
1#
#8320000
0#
b100010 0
#8330000
b100011 *
1#
#8340000
0#
b100011 0
#8350000
b100100 *
1#
#8360000
0#
b100100 0
#8370000
b100101 *
1#
#8380000
0#
b100101 0
#8390000
b100110 *
1#
#8400000
0#
b100110 0
#8410000
b100111 *
1#
#8420000
0#
b100111 0
#8430000
b101000 *
1#
#8440000
0#
b101000 0
#8450000
b101001 *
1#
#8460000
0#
b101001 0
#8470000
b101010 *
1#
#8480000
0#
b101010 0
#8490000
b101011 *
1#
#8500000
0#
b101011 0
#8510000
b101100 *
1#
#8520000
0#
b101100 0
#8530000
b101101 *
1#
#8540000
0#
b101101 0
#8550000
b101110 *
1#
#8560000
0#
b101110 0
#8570000
b101111 *
1#
#8580000
0#
b101111 0
#8590000
b110000 *
1#
#8600000
0#
b110000 0
#8610000
b110001 *
1#
#8620000
0#
b110001 0
#8630000
b110010 *
1#
#8640000
0#
b110010 0
#8650000
b110011 *
1#
#8660000
0#
b110011 0
#8670000
b110100 *
1#
#8680000
0#
b110100 0
#8690000
b110101 *
1#
#8700000
0#
b110101 0
#8710000
b110110 *
1#
#8720000
0#
b110110 0
#8730000
b110111 *
1#
#8740000
0#
b110111 0
#8750000
b10 )
b0 *
1#
#8760000
0#
b111000 0
#8770000
b1 +
1#
#8780000
0#
b11 &
b11 '
b1 1
#8790000
b0 )
b0 +
1#
#8800000
0#
b1 &
b1 '
b10 1
#8810000
b1 *
b1 )
1#
#8820000
0#
b11 &
b11 '
b11 1
#8830000
b0 )
b0 *
1#
#8840000
0#
b100 1
#8850000
1#
#8860000
0#
b1 2
#8870000
1#
#8880000
0#
b10 2
#8890000
1#
#8900000
0#
b11 2
#8910000
1#
#8920000
0#
b100 2
#8930000
1#
#8940000
0#
b101 2
#8950000
1#
#8960000
0#
b110 2
#8970000
1#
#8980000
0#
b111 2
#8990000
1#
#9000000
0#
b1000 2
#9010000
1#
#9020000
0#
b1001 2
#9030000
1#
#9040000
0#
b1010 2
#9050000
1#
#9060000
0#
b1011 2
#9070000
1#
#9080000
0#
b1100 2
#9090000
1#
#9100000
0#
b1101 2
