src/firewall.sv
`default_nettype none
`timescale 1ns / 1ps
module firewall(
	input wire clk,
	input wire rst,
	input wire axiiv,
	input wire[1:0] axiid,

	output logic axiov,
	output logic[1:0] axiod
);

//logic [47:0] mac_addr
logic[5:0] bit_count;
logic[47:0] mac;
localparam mac_addr = 48'h69_69_5A_06_54_91;
logic is_broadcast;
logic is_my_addr;
logic can_recieve_data;
//logic[23:0] axiod_pipe[1:0];
//logic [23:0] axiov_pipe;
logic is_data_valid;
assign mac = mac_addr;
always_ff @(posedge clk)begin
	if(rst)begin
		bit_count <= 0;
		can_recieve_data <= 0;
		is_my_addr <= 1;
		is_broadcast <= 1;
	end

	if(axiiv)begin
		if(is_my_addr)begin
			if(bit_count == 0 && mac_addr[47:46] != axiid)
				is_my_addr <= 0;
			else if(bit_count == 1 && mac_addr[45:44] != axiid)
                                is_my_addr <= 0;
			else if(bit_count == 2 && mac_addr[43:42] != axiid)
                                is_my_addr <= 0;
			else if(bit_count == 3 && mac_addr[41:40] != axiid)
                                is_my_addr <= 0;
			else if(bit_count == 4 && mac_addr[39:38] != axiid)
                                is_my_addr <= 0;
			else if(bit_count == 5 && mac_addr[37:36] != axiid)
                                is_my_addr <=0;
			else if(bit_count == 6 && mac_addr[35:34] != axiid)
                                is_my_addr <= 0;
			else if(bit_count == 7 && mac_addr[33:32] != axiid)
                                is_my_addr <= 0;
			else if(bit_count == 8 && mac_addr[31:30] != axiid)
                                is_my_addr <= 0;
			else if(bit_count == 9 && mac_addr[29:28] != axiid)
                                is_my_addr <= 0;
			else if(bit_count == 10 && mac_addr[27:26] != axiid)
                                is_my_addr <= 0;
			else if(bit_count == 11 && mac_addr[25:24] != axiid)
                                is_my_addr <= 0;
			else if(bit_count == 12 && mac_addr[23:22] != axiid)
                                is_my_addr <= 0;
			else if(bit_count == 13 && mac_addr[21:20] != axiid)
                                is_my_addr <= 0;
			else if(bit_count == 14 && mac_addr[19:18] != axiid)
                                is_my_addr <= 0;
			else if(bit_count == 15 && mac_addr[17:16] != axiid)
                                is_my_addr <= 0;
			else if(bit_count == 16 && mac_addr[15:14] != axiid)
                                is_my_addr <= 0;
			else if(bit_count == 17 && mac_addr[13:12] != axiid)
                                is_my_addr <= 0;
			else if(bit_count == 18 && mac_addr[11:10] != axiid)
                                is_my_addr <= 0;
			else if(bit_count == 19 && mac_addr[9:8] != axiid)
                                is_my_addr <= 0;
			else if(bit_count == 20 && mac_addr[7:6] != axiid)
                                is_my_addr <= 0;
			else if(bit_count == 21 && mac_addr[5:4] != axiid)
                                is_my_addr <= 0;
			else if(bit_count == 22 && mac_addr[3:2] != axiid)
                                is_my_addr <= 0;
			else if(bit_count == 23 && mac_addr[1:0] != axiid)
                                is_my_addr <= 0;
		end
		if(is_broadcast)begin
			if(bit_count < 24 && 2'b11 != axiid)
				is_broadcast <= 0;
		end
		if(bit_count < 56)
			bit_count <= bit_count + 1;

		if(bit_count == 24)begin
			if(is_broadcast || is_my_addr)
				can_recieve_data <= 1;
		end
		/*if(can_recieve_data && bit_count == 56)begin
			is_data_valid <= 1;
		end*/
	end
	else begin
		//is_data_valid <= 0;
		bit_count <= 0;
		is_broadcast <= 1;
		is_my_addr <= 1;
		can_recieve_data <= 0;
		//is_data_valid <= 0;
	end
end


assign axiov = is_data_valid && axiiv;
assign axiod = axiid;
assign is_data_valid = can_recieve_data && bit_count == 56 ? 1:0; 

endmodule
`default_nettype wire

sim/firewall_tb.sv
`default_nettype none
`timescale 1ns / 1ps

module firewall_tb;

logic clk;
logic rst;
logic axiiv;
logic[1:0] axiid;

logic axiov;
logic[1:0] axiod;

firewall uut(
	.clk(clk),
	.rst(rst),
	.axiiv(axiiv),
	.axiid(axiid),
	.axiov(axiov),
	.axiod(axiod)
);

localparam mac_addr = 48'h69_69_5A_06_54_91;

always begin
	#10;
       	clk = !clk;
end

initial begin
	$dumpfile("firewall.vcd");
	$dumpvars(0,firewall_tb);
	$display("Starting Sim");
	clk = 1;
	#20;
	rst = 1;
	#20;
	rst = 0;
	#20;
	axiiv = 1;
	for(int i = 0;i<24;i = i +1)begin
		case(i)
			0:axiid = mac_addr[47:46];
			1:axiid = mac_addr[45:44];
			2:axiid = mac_addr[43:42];
			3:axiid = mac_addr[41:40];
			4:axiid = mac_addr[39:38];
			5:axiid = mac_addr[37:36];
			6:axiid = mac_addr[35:34];
			7:axiid = mac_addr[33:32];
			8:axiid = mac_addr[31:30];
			9:axiid = mac_addr[29:28];
			10:axiid = mac_addr[27:26];
			11:axiid = mac_addr[25:24];
			12:axiid = mac_addr[23:22];
			13:axiid = mac_addr[21:20];
			14:axiid = mac_addr[19:18];
			15:axiid = mac_addr[17:16];
			16:axiid = mac_addr[15:14];
			17:axiid = mac_addr[13:12];
			18:axiid = mac_addr[11:10];
			19:axiid = mac_addr[9:8];
			20:axiid = mac_addr[7:6];
			21:axiid = mac_addr[5:4];
			22:axiid = mac_addr[3:2];
			23:axiid = mac_addr[1:0];
		endcase
		#20;
	end

	for(int i = 0;i<24;i = i + 1)begin
		axiid = 2'b01;
		#20;
	end
	for(int i = 0;i<8;i = i+1)begin
		axiid = 2'b11;
		#20;
	end
	for(int i = 0;i<24;i = i+1)begin
		axiid = i%2 == 0 ? 2'b01:2'b10;
		#20;
	end
	axiiv = 0;
	#1000;
	axiiv = 1;
	for(int i = 0;i<24;i=i+1)begin
		axiid = 2'b11;
		#20;
	end
	for(int i = 0;i<24;i = i + 1)begin
                axiid = 2'b01;
                #20;
        end
        for(int i = 0;i<8;i = i+1)begin
                axiid = 2'b11;
                #20;
        end
        for(int i = 0;i<24;i = i+1)begin
                axiid = i%2 == 0 ? 2'b01:2'b10;
                #20;
        end
	axiiv = 0;
	#1000
	$display("Finishing Sim");
	$finish;
end

endmodule
`default_nettype wire

firewall.vcd
$date
	Thu Oct 27 21:59:20 2022
$end
$version
	Icarus Verilog
$end
$timescale
	1ps
$end
$scope module firewall_tb $end
$var wire 1 ! axiov $end
$var wire 2 " axiod [1:0] $end
$var reg 2 # axiid [1:0] $end
$var reg 1 $ axiiv $end
$var reg 1 % clk $end
$var reg 1 & rst $end
$scope module uut $end
$var wire 2 ' axiid [1:0] $end
$var wire 1 $ axiiv $end
$var wire 2 ( axiod [1:0] $end
$var wire 1 ! axiov $end
$var wire 1 % clk $end
$var wire 48 ) mac [47:0] $end
$var wire 1 & rst $end
$var wire 1 * is_data_valid $end
$var reg 6 + bit_count [5:0] $end
$var reg 1 , can_recieve_data $end
$var reg 1 - is_broadcast $end
$var reg 1 . is_my_addr $end
$upscope $end
$scope begin $ivl_for_loop0 $end
$var integer 32 / i [31:0] $end
$upscope $end
$scope begin $ivl_for_loop1 $end
$var integer 32 0 i [31:0] $end
$upscope $end
$scope begin $ivl_for_loop2 $end
$var integer 32 1 i [31:0] $end
$upscope $end
$scope begin $ivl_for_loop3 $end
$var integer 32 2 i [31:0] $end
$upscope $end
$scope begin $ivl_for_loop4 $end
$var integer 32 3 i [31:0] $end
$upscope $end
$scope begin $ivl_for_loop5 $end
$var integer 32 4 i [31:0] $end
$upscope $end
$scope begin $ivl_for_loop6 $end
$var integer 32 5 i [31:0] $end
$upscope $end
$scope begin $ivl_for_loop7 $end
$var integer 32 6 i [31:0] $end
$upscope $end
$upscope $end
$enddefinitions $end
#0
$dumpvars
b0 6
b0 5
b0 4
b0 3
b0 2
b0 1
b0 0
b0 /
1.
1-
0,
b0 +
0*
b11010010110100101011010000001100101010010010001 )
bx (
bx '
x&
1%
x$
bx #
bx "
0!
$end
#10000
0%
#20000
1%
1&
#30000
0%
#40000
1%
0&
#50000
0%
#60000
b1 +
0-
1%
b1 "
b1 (
b1 #
b1 '
1$
#70000
0%
#80000
b10 +
1%
b10 "
b10 (
b10 #
b10 '
b1 /
#90000
0%
#100000
b11 +
1%
b10 /
#110000
0%
#120000
b100 +
1%
b1 "
b1 (
b1 #
b1 '
b11 /
#130000
0%
#140000
b101 +
1%
b100 /
#150000
0%
#160000
b110 +
1%
b10 "
b10 (
b10 #
b10 '
b101 /
#170000
0%
#180000
b111 +
1%
b110 /
#190000
0%
#200000
b1000 +
1%
b1 "
b1 (
b1 #
b1 '
b111 /
#210000
0%
#220000
b1001 +
1%
b1000 /
#230000
0%
#240000
b1010 +
1%
b1001 /
#250000
0%
#260000
b1011 +
1%
b10 "
b10 (
b10 #
b10 '
b1010 /
#270000
0%
#280000
b1100 +
1%
b1011 /
#290000
0%
#300000
b1101 +
1%
b0 "
b0 (
b0 #
b0 '
b1100 /
#310000
0%
#320000
b1110 +
1%
b1101 /
#330000
0%
#340000
b1111 +
1%
b1 "
b1 (
b1 #
b1 '
b1110 /
#350000
0%
#360000
b10000 +
1%
b10 "
b10 (
b10 #
b10 '
b1111 /
#370000
0%
#380000
b10001 +
1%
b1 "
b1 (
b1 #
b1 '
b10000 /
#390000
0%
#400000
b10010 +
1%
b10001 /
#410000
0%
#420000
b10011 +
1%
b10010 /
#430000
0%
#440000
b10100 +
1%
b0 "
b0 (
b0 #
b0 '
b10011 /
#450000
0%
#460000
b10101 +
1%
b10 "
b10 (
b10 #
b10 '
b10100 /
#470000
0%
#480000
b10110 +
1%
b1 "
b1 (
b1 #
b1 '
b10101 /
#490000
0%
#500000
b10111 +
1%
b0 "
b0 (
b0 #
b0 '
b10110 /
#510000
0%
#520000
b11000 +
1%
b1 "
b1 (
b1 #
b1 '
b10111 /
#530000
0%
#540000
1,
b11001 +
1%
b11000 /
#550000
0%
#560000
b11010 +
1%
b1 0
#570000
0%
#580000
b11011 +
1%
b10 0
#590000
0%
#600000
b11100 +
1%
b11 0
#610000
0%
#620000
b11101 +
1%
b100 0
#630000
0%
#640000
b11110 +
1%
b101 0
#650000
0%
#660000
b11111 +
1%
b110 0
#670000
0%
#680000
b100000 +
1%
b111 0
#690000
0%
#700000
b100001 +
1%
b1000 0
#710000
0%
#720000
b100010 +
1%
b1001 0
#730000
0%
#740000
b100011 +
1%
b1010 0
#750000
0%
#760000
b100100 +
1%
b1011 0
#770000
0%
#780000
b100101 +
1%
b1100 0
#790000
0%
#800000
b100110 +
1%
b1101 0
#810000
0%
#820000
b100111 +
1%
b1110 0
#830000
0%
#840000
b101000 +
1%
b1111 0
#850000
0%
#860000
b101001 +
1%
b10000 0
#870000
0%
#880000
b101010 +
1%
b10001 0
#890000
0%
#900000
b101011 +
1%
b10010 0
#910000
0%
#920000
b101100 +
1%
b10011 0
#930000
0%
#940000
b101101 +
1%
b10100 0
#950000
0%
#960000
b101110 +
1%
b10101 0
#970000
0%
#980000
b101111 +
1%
b10110 0
#990000
0%
#1000000
b110000 +
1%
b10111 0
#1010000
0%
#1020000
b110001 +
1%
b11 "
b11 (
b11 #
b11 '
b11000 0
#1030000
0%
#1040000
b110010 +
1%
b1 1
#1050000
0%
#1060000
b110011 +
1%
b10 1
#1070000
0%
#1080000
b110100 +
1%
b11 1
#1090000
0%
#1100000
b110101 +
1%
b100 1
#1110000
0%
#1120000
b110110 +
1%
b101 1
#1130000
0%
#1140000
b110111 +
1%
b110 1
#1150000
0%
#1160000
1!
1*
b111000 +
1%
b111 1
#1170000
0%
#1180000
1%
b1 "
b1 (
b1 #
b1 '
b1000 1
#1190000
0%
#1200000
1%
b10 "
b10 (
b10 #
b10 '
b1 2
#1210000
0%
#1220000
1%
b1 "
b1 (
b1 #
b1 '
b10 2
#1230000
0%
#1240000
1%
b10 "
b10 (
b10 #
b10 '
b11 2
#1250000
0%
#1260000
1%
b1 "
b1 (
b1 #
b1 '
b100 2
#1270000
0%
#1280000
1%
b10 "
b10 (
b10 #
b10 '
b101 2
#1290000
0%
#1300000
1%
b1 "
b1 (
b1 #
b1 '
b110 2
#1310000
0%
#1320000
1%
b10 "
b10 (
b10 #
b10 '
b111 2
#1330000
0%
#1340000
1%
b1 "
b1 (
b1 #
b1 '
b1000 2
#1350000
0%
#1360000
1%
b10 "
b10 (
b10 #
b10 '
b1001 2
#1370000
0%
#1380000
1%
b1 "
b1 (
b1 #
b1 '
b1010 2
#1390000
0%
#1400000
1%
b10 "
b10 (
b10 #
b10 '
b1011 2
#1410000
0%
#1420000
1%
b1 "
b1 (
b1 #
b1 '
b1100 2
#1430000
0%
#1440000
1%
b10 "
b10 (
b10 #
b10 '
b1101 2
#1450000
0%
#1460000
1%
b1 "
b1 (
b1 #
b1 '
b1110 2
#1470000
0%
#1480000
1%
b10 "
b10 (
b10 #
b10 '
b1111 2
#1490000
0%
#1500000
1%
b1 "
b1 (
b1 #
b1 '
b10000 2
#1510000
0%
#1520000
1%
b10 "
b10 (
b10 #
b10 '
b10001 2
#1530000
0%
#1540000
1%
b1 "
b1 (
b1 #
b1 '
b10010 2
#1550000
0%
#1560000
1%
b10 "
b10 (
b10 #
b10 '
b10011 2
#1570000
0%
#1580000
1%
b1 "
b1 (
b1 #
b1 '
b10100 2
#1590000
0%
#1600000
1%
b10 "
b10 (
b10 #
b10 '
b10101 2
#1610000
0%
#1620000
1%
b1 "
b1 (
b1 #
b1 '
b10110 2
#1630000
0%
#1640000
1%
b10 "
b10 (
b10 #
b10 '
b10111 2
#1650000
0%
#1660000
0!
0*
0,
1-
b0 +
1%
0$
b11000 2
